{"country": "INDO", "eventType": "Indo_new_403", "orderId": "id003hxfk202604131055232393314", "applyTime": 1776053075000, "params": {"base": {"appname": "teman-pinjam", "newCustomer": 1, "birthday": "29-01-1995", "job": "4", "channel": "未知渠道", "applyTime": 1776053075000, "gender": 0, "phone": "+6281231742469", "gaid": "83eff810-3a2b-4486-808c-141e4a0b6830", "bankCard": "1240577778", "idCard": "3507056901950004", "marita": 1, "children": 0, "salary": 4000000, "workYears": 4, "state": 0, "relationship1": 4, "relationship2": 5, "use": 4, "uaClientType": "Android", "orderSource": "self", "userTg": "XJX_0", "packageName": "com.temanpinjam.uangpinjammikro"}, "appList": [{"inTime": 23549926, "upTime": 1757574328261, "appName": "Dokumen", "appType": 0, "versionName": "16.6.2", "packageX": "andes.oplus.documentsreader", "versionCode": "16.6.2"}, {"inTime": 1776052080277, "upTime": 1776052080277, "appName": "Lumbung Dana", "appType": 0, "versionName": "1.3.17", "packageX": "co.id.lumbungdana.android", "versionCode": "1.3.17"}, {"inTime": 1759739331665, "upTime": 1759739331665, "appName": "Ojek Online The Game", "appType": 0, "versionName": "3.4.0", "packageX": "codexplore.ojol", "versionCode": "3.4.0"}, {"inTime": 23551787, "upTime": 23551787, "appName": "Tile Match", "appType": 0, "versionName": "2.2", "packageX": "com.KatanLabs.tilematchpuzzlemaster", "versionCode": "2.2"}, {"inTime": 1775973778116, "upTime": 1775973778116, "appName": "Ada Dana", "appType": 0, "versionName": "1.0.2", "packageX": "com.ada.dana", "versionCode": "1.0.2"}, {"inTime": 1768740298174, "upTime": 1773308009757, "appName": "AdaKami", "appType": 0, "versionName": "7.13.0", "packageX": "com.adakami.dana.kredit.pinjaman", "versionCode": "7.13.0"}, {"inTime": 23553101, "upTime": 23553101, "appName": "Agoda", "appType": 0, "versionName": "12.34.0", "packageX": "com.agoda.mobile.consumer", "versionCode": "12.34.0"}, {"inTime": 1750315502525, "upTime": 1774215757419, "appName": "Jadwal Sholat", "appType": 0, "versionName": "1.18.3", "packageX": "com.andi.waktusholatdankiblat", "versionCode": "1.18.3"}, {"inTime": 1775998295126, "upTime": 1775998295126, "appName": "Singa", "appType": 0, "versionName": "3.0.9", "packageX": "com.asf.singa", "versionCode": "3.0.9"}, {"inTime": 1750315195403, "upTime": 1771030769445, "appName": "BCA mobile", "appType": 0, "versionName": "4.7.9", "packageX": "com.bca", "versionCode": "4.7.9"}, {"inTime": 1759887787874, "upTime": 1775689914438, "appName": "Lemon8", "appType": 0, "versionName": "12.2.1", "packageX": "com.bd.nproject", "versionCode": "12.2.1"}, {"inTime": 23550249, "upTime": 1775858967728, "appName": "Block Blast!", "appType": 0, "versionName": "9.6.1", "packageX": "com.block.juggle", "versionCode": "9.6.1"}, {"inTime": 23553161, "upTime": 23553161, "appName": "Booking.com", "appType": 0, "versionName": "43.6.101", "packageX": "com.booking", "versionCode": "43.6.101"}, {"inTime": 1762599284423, "upTime": 1762599284423, "appName": "Smart Budget: Money Tracker", "appType": 0, "versionName": "1.0.2", "packageX": "com.budgettracker.personalfinance.trackmoney.smartbudget", "versionCode": "1.0.2"}, {"inTime": 1775618153455, "upTime": 1775858976719, "appName": "UangMe", "appType": 0, "versionName": "4.0.3", "packageX": "com.cmcm.uangme", "versionCode": "4.0.3"}, {"inTime": 23549449, "upTime": 23549449, "appName": "Clone Phone", "appType": 0, "versionName": "16.10.0", "packageX": "com.coloros.backuprestore", "versionCode": "16.10.0"}, {"inTime": 23549712, "upTime": 23549712, "appName": "Pesta Musik", "appType": 0, "versionName": "15.0.22", "packageX": "com.coloros.musiclink", "versionCode": "15.0.22"}, {"inTime": 23549765, "upTime": 1770402965675, "appName": "Catatan", "appType": 0, "versionName": "16.2.62", "packageX": "com.coloros.note", "versionCode": "16.2.62"}, {"inTime": 23549477, "upTime": 23549477, "appName": "Kunci Layar", "appType": 0, "versionName": "15.0.3", "packageX": "com.coloros.onekeylockscreen", "versionCode": "15.0.3"}, {"inTime": 23549598, "upTime": 23549598, "appName": "Terjemahkan", "appType": 0, "versionName": "16.0.24", "packageX": "com.coloros.translate", "versionCode": "16.0.24"}, {"inTime": 1767877986270, "upTime": 1770543383152, "appName": "Marble Match Origin", "appType": 0, "versionName": "1.1.60", "packageX": "com.core.biggame.marble.android", "versionCode": "1.1.60"}, {"inTime": 1765112984351, "upTime": 1771113648562, "appName": "Aplikasi Keuangan", "appType": 0, "versionName": "1.3", "packageX": "com.debit.scope.mark", "versionCode": "1.3"}, {"inTime": 1773980401276, "upTime": 1773980401276, "appName": "Dana Digital", "appType": 0, "versionName": "1.6.1", "packageX": "com.dndigit.pnjaanung", "versionCode": "1.6.1"}, {"inTime": 1767877960079, "upTime": 1773396616539, "appName": "Plants Vs Zombies 2", "appType": 0, "versionName": "13.0.1", "packageX": "com.ea.game.pvz2_row", "versionCode": "13.0.1"}, {"inTime": 1767672084021, "upTime": 1773528855754, "appName": "Plants vs. Zombies FREE", "appType": 0, "versionName": "3.15.0", "packageX": "com.ea.game.pvzfree_row", "versionCode": "3.15.0"}, {"inTime": 1765112687681, "upTime": 1767821536152, "appName": "Dana Cepat", "appType": 0, "versionName": "2.0.2", "packageX": "com.exploresia", "versionCode": "2.0.2"}, {"inTime": 23549139, "upTime": 1776023459598, "appName": "Facebook", "appType": 0, "versionName": "556.0.0.60.64", "packageX": "com.facebook.katana", "versionCode": "556.0.0.60.64"}, {"inTime": 1750315547640, "upTime": 1776041273438, "appName": "Messenger", "appType": 0, "versionName": "556.0.0.59.68", "packageX": "com.facebook.orca", "versionCode": "556.0.0.59.68"}, {"inTime": 1771217572961, "upTime": 1773396412888, "appName": "FinPlus", "appType": 0, "versionName": "1.7.45", "packageX": "com.finplus.android", "versionCode": "1.7.45"}, {"inTime": 1750359018588, "upTime": 1750359018588, "appName": "Fineasy", "appType": 0, "versionName": "2.13.22", "packageX": "com.fintech.life", "versionCode": "2.13.22"}, {"inTime": 23549529, "upTime": 23549529, "appName": "Fitbit", "appType": 0, "versionName": "4.41.fitbit-mobile-110273285-746279103", "packageX": "com.fitbit.FitbitMobile", "versionCode": "4.41.fitbit-mobile-110273285-746279103"}, {"inTime": 23550106, "upTime": 23550106, "appName": "AquaBlocks Puzzle Seas", "appType": 0, "versionName": "1.7", "packageX": "com.fullmetalgamedev.aquablockspuzzleseas", "versionCode": "1.7"}, {"inTime": 23550113, "upTime": 23550113, "appName": "Fruit Shooting- Sharp Knife", "appType": 0, "versionName": "1.8", "packageX": "com.fullmetalgamedev.fruitshooting", "versionCode": "1.8"}, {"inTime": 23550251, "upTime": 23550251, "appName": "Space Cruises Shooting game", "appType": 0, "versionName": "2.6", "packageX": "com.fullmetalgamedev.ultimatecruises", "versionCode": "2.6"}, {"inTime": 23552654, "upTime": 23552654, "appName": "Joy Games", "appType": 0, "versionName": "v1.2.27_pre", "packageX": "com.games.yikegames", "versionCode": "v1.2.27_pre"}, {"inTime": 1750315453833, "upTime": 1775858836336, "appName": "Gojek", "appType": 0, "versionName": "5.55.2", "packageX": "com.gojek.app", "versionCode": "5.55.2"}, {"inTime": 1772368216273, "upTime": 1775689658978, "appName": "GoPay", "appType": 0, "versionName": "2.6.0", "packageX": "com.gojek.gopay", "versionCode": "2.6.0"}, {"inTime": 23549172, "upTime": 23549172, "appName": "Hub Pencari", "appType": 0, "versionName": "3.1.348", "packageX": "com.google.android.apps.adm", "versionCode": "3.1.348"}, {"inTime": 1750315445359, "upTime": 1775519382679, "appName": "Google Play Buku", "appType": 0, "versionName": "2026.3.6.1 (350436)", "packageX": "com.google.android.apps.books", "versionCode": "2026.3.6.1 (350436)"}, {"inTime": 23549685, "upTime": 23549685, "appName": "Home", "appType": 0, "versionName": "3.41.50.4", "packageX": "com.google.android.apps.chromecast.app", "versionCode": "3.41.50.4"}, {"inTime": 23549325, "upTime": 1775689849845, "appName": "Drive", "appType": 0, "versionName": "2.26.137.2.all.alldpi", "packageX": "com.google.android.apps.docs", "versionCode": "2.26.137.2.all.alldpi"}, {"inTime": 1750315450785, "upTime": 1775166398133, "appName": "Google Berita", "appType": 0, "versionName": "5.155.0.892577434", "packageX": "com.google.android.apps.magazines", "versionCode": "5.155.0.892577434"}, {"inTime": 1750315438242, "upTime": 1768686504846, "appName": "Google Podcasts", "appType": 0, "versionName": "1.0.0.728820940", "packageX": "com.google.android.apps.podcasts", "versionCode": "1.0.0.728820940"}, {"inTime": 23549225, "upTime": 1775689858080, "appName": "Google One", "appType": 0, "versionName": "1.304.892470692", "packageX": "com.google.android.apps.subscriptions.red", "versionCode": "1.304.892470692"}, {"inTime": 23549505, "upTime": 1775345518235, "appName": "YouTube Music", "appType": 0, "versionName": "9.13.50", "packageX": "com.google.android.apps.youtube.music", "versionCode": "9.13.50"}, {"inTime": 23549400, "upTime": 1775166344660, "appName": "Google TV", "appType": 0, "versionName": "4.39.4323.888244609.2-release", "packageX": "com.google.android.videos", "versionCode": "4.39.4323.888244609.2-release"}, {"inTime": 1750410487907, "upTime": 1775430095390, "appName": "Grab", "appType": 0, "versionName": "5.404.1", "packageX": "com.grabtaxi.passenger", "versionCode": "5.404.1"}, {"inTime": 1750315597006, "upTime": 1750315597006, "appName": "OPPO Store", "appType": 0, "versionName": "1.6.5", "packageX": "com.heytap.mall", "versionCode": "1.6.5"}, {"inTime": 1768603630020, "upTime": 1769779110156, "appName": "KrediOne(360Kredi)", "appType": 0, "versionName": "3.1.9", "packageX": "com.id.kredi360", "versionCode": "3.1.9"}, {"inTime": 1775999315365, "upTime": 1775999315365, "appName": "Indosaku", "appType": 0, "versionName": "2.4.0", "packageX": "com.indosk.sensid", "versionCode": "2.4.0"}, {"inTime": 1750315463760, "upTime": 1775785809570, "appName": "Instagram", "appType": 0, "versionName": "424.0.0.49.64", "packageX": "com.instagram.android", "versionCode": "424.0.0.49.64"}, {"inTime": 1750316011366, "upTime": 1775786120142, "appName": "Threads", "appType": 0, "versionName": "424.0.0.48.68", "packageX": "com.instagram.barcelona", "versionCode": "424.0.0.48.68"}, {"inTime": 1771652192093, "upTime": 1775975964088, "appName": "Cairin", "appType": 0, "versionName": "3.4.2", "packageX": "com.iss.client.cairin", "versionCode": "3.4.2"}, {"inTime": 1750315504049, "upTime": 1768871638020, "appName": "Juragan99 Trans", "appType": 0, "versionName": "5.0.18", "packageX": "com.juragan99trans.id", "versionCode": "5.0.18"}, {"inTime": 23550156, "upTime": 1774985949615, "appName": "Bubble Pop! - Shooter Puzzle", "appType": 0, "versionName": "8.6", "packageX": "com.katanlabs.bubblepop", "versionCode": "8.6"}, {"inTime": 23550263, "upTime": 23550263, "appName": "Collect Ball - Match Em All", "appType": 0, "versionName": "3.5", "packageX": "com.katanlabs.matchballgame", "versionCode": "3.5"}, {"inTime": 23551707, "upTime": 23551707, "appName": "Word Connect Wonders Of View", "appType": 0, "versionName": "2.8", "packageX": "com.katanlabs.wordconnectwondersofview", "versionCode": "2.8"}, {"inTime": 23552098, "upTime": 23552098, "appName": "Worm family - Eat em All", "appType": 0, "versionName": "3.5", "packageX": "com.katanlabs.worm.ioeatemall", "versionCode": "3.5"}, {"inTime": 1771384833353, "upTime": 1771384833353, "appName": "Pinjam Yuk", "appType": 0, "versionName": "2.3.7", "packageX": "com.kkii", "versionCode": "2.3.7"}, {"inTime": 1776035233137, "upTime": 1776035233137, "appName": "klikUMKM", "appType": 0, "versionName": "2.4.0", "packageX": "com.klik.klikUMKM", "versionCode": "2.4.0"}, {"inTime": 1773108574236, "upTime": 1773108574236, "appName": "Kredito", "appType": 0, "versionName": "4.1.2", "packageX": "com.kredito.fintek", "versionCode": "4.1.2"}, {"inTime": 1761146249596, "upTime": 1775689666858, "appName": "Kredit Pintar", "appType": 0, "versionName": "1.12.5", "packageX": "com.kreditpintar", "versionCode": "1.12.5"}, {"inTime": 1776052297771, "upTime": 1776052297771, "appName": "KTA KILAT", "appType": 0, "versionName": "5.3.8", "packageX": "com.ktakilat.loan", "versionCode": "5.3.8"}, {"inTime": 23553485, "upTime": 1775166326205, "appName": "Lazada", "appType": 0, "versionName": "7.96.0", "packageX": "com.lazada.android", "versionCode": "7.96.0"}, {"inTime": 1750315230946, "upTime": 1775689642230, "appName": "CapCut", "appType": 0, "versionName": "17.4.0", "packageX": "com.lemon.lvoverseas", "versionCode": "17.4.0"}, {"inTime": 23553577, "upTime": 23553577, "appName": "LinkedIn", "appType": 0, "versionName": "4.1.925", "packageX": "com.linkedin.android", "versionCode": "4.1.925"}, {"inTime": 1771213137575, "upTime": 1775166212721, "appName": "Rupiah Cepat", "appType": 0, "versionName": "3.7.2", "packageX": "com.loan.cash.credit.easy.kilat.cepat.pinjam.uang.dana.rupiah", "versionCode": "3.7.2"}, {"inTime": 23553350, "upTime": 23553350, "appName": "J&T Express", "appType": 0, "versionName": "V3.24.3", "packageX": "com.msd.JTClient", "versionCode": "V3.24.3"}, {"inTime": 1750315526687, "upTime": 1750315526687, "appName": "Muslim Sholat Pro", "appType": 0, "versionName": "2.37", "packageX": "com.muslimramadantech.praytimes.azanreminder", "versionCode": "2.37"}, {"inTime": 23547767, "upTime": 1774515231114, "appName": "Game Center", "appType": 0, "versionName": "16.8.0", "packageX": "com.nearme.gamecenter", "versionCode": "16.8.0"}, {"inTime": 23553119, "upTime": 1775345445112, "appName": "Netflix", "appType": 0, "versionName": "9.60.0 build 4 63988", "packageX": "com.netflix.mediaclient", "versionCode": "9.60.0 build 4 63988"}, {"inTime": 23552678, "upTime": 23552678, "appName": "ReelShort", "appType": 0, "versionName": "2.0.20", "packageX": "com.newleaf.app.android.victor", "versionCode": "2.0.20"}, {"inTime": 1767879995029, "upTime": 1767879995029, "appName": "Tile Explorer", "appType": 0, "versionName": "1.68.2", "packageX": "com.oakever.tiletrip", "versionCode": "1.68.2"}, {"inTime": 23549665, "upTime": 1775249742245, "appName": "Zen Space", "appType": 0, "versionName": "16.7.0", "packageX": "com.oneplus.brickmode", "versionCode": "16.7.0"}, {"inTime": 1759739360567, "upTime": 1759739360567, "appName": "Opera", "appType": 0, "versionName": "91.6.4817.85486", "packageX": "com.opera.browser", "versionCode": "91.6.4817.85486"}, {"inTime": 23549693, "upTime": 23549693, "appName": "AI Studio", "appType": 0, "versionName": "3.1.2", "packageX": "com.oplus.ai.magicstudio", "versionCode": "3.1.2"}, {"inTime": 23549493, "upTime": 23549493, "appName": "OPPO Saya", "appType": 0, "versionName": "EXP_8.61.3", "packageX": "com.oplus.member", "versionCode": "EXP_8.61.3"}, {"inTime": 1765105295461, "upTime": 1775858973569, "appName": "Solusiku", "appType": 0, "versionName": "7.0.5.0", "packageX": "com.qm.adi", "versionCode": "7.0.5.0"}, {"inTime": 1750315536595, "upTime": 1755933178119, "appName": "MTrans Connect", "appType": 0, "versionName": "2.3.0", "packageX": "com.rongrit.mtrans", "versionCode": "2.3.0"}, {"inTime": 1770507438044, "upTime": 1775091246985, "appName": "Samir", "appType": 0, "versionName": "2.9.0", "packageX": "com.sahabatmikro", "versionCode": "2.9.0"}, {"inTime": 1768645231922, "upTime": 1768645231922, "appName": "Girl Rescue", "appType": 0, "versionName": "1.0.5.0", "packageX": "com.save.princess.girl.dragon.out.and", "versionCode": "1.0.5.0"}, {"inTime": 1776034942474, "upTime": 1776034942474, "appName": "PinjamPasti", "appType": 0, "versionName": "2.3.0", "packageX": "com.seekforpinjaman.pinjampasti", "versionCode": "2.3.0"}, {"inTime": 1772428662856, "upTime": 1775166171476, "appName": "ShieldMe", "appType": 0, "versionName": "1.17", "packageX": "com.shieldme.applock.pin.pattern", "versionCode": "1.17"}, {"inTime": 23553654, "upTime": 1775858988922, "appName": "Shopee", "appType": 0, "versionName": "3.71.26", "packageX": "com.shopee.id", "versionCode": "3.71.26"}, {"inTime": 1750315525041, "upTime": 1775858889759, "appName": "ShopeePay", "appType": 0, "versionName": "1.52.04", "packageX": "com.shopeepay.id", "versionCode": "1.52.04"}, {"inTime": 1774318902910, "upTime": 1774318902910, "appName": "BantuSaku", "appType": 0, "versionName": "3.7.7.1", "packageX": "com.smartec.ft", "versionCode": "3.7.7.1"}, {"inTime": 23553568, "upTime": 23553568, "appName": "Spotify", "appType": 0, "versionName": "8.9.40.509", "packageX": "com.spotify.music", "versionCode": "8.9.40.509"}, {"inTime": 23554465, "upTime": 1775689524223, "appName": "TikTok", "appType": 0, "versionName": "44.6.4", "packageX": "com.ss.android.ugc.trill", "versionCode": "44.6.4"}, {"inTime": 1771450463119, "upTime": 1774306205214, "appName": "PinjamDuit", "appType": 0, "versionName": "7.5.0", "packageX": "com.stanfordtek.pinjamduit", "versionCode": "7.5.0"}, {"inTime": 1776052432785, "upTime": 1776052432785, "appName": "TemanPinjam", "appType": 0, "versionName": "1.0", "packageX": "com.temanpinjam.uangpinjammikro", "versionCode": "1.0"}, {"inTime": 23552621, "upTime": 1775689581967, "appName": "TOMORO COFFEE", "appType": 0, "versionName": "3.4.2", "packageX": "com.tomoro.indonesia.android", "versionCode": "3.4.2"}, {"inTime": 1750315853583, "upTime": 1775166156267, "appName": "Traveloka", "appType": 0, "versionName": "5.41.1", "packageX": "com.traveloka.android", "versionCode": "5.41.1"}, {"inTime": 1750316009132, "upTime": 1750316009132, "appName": "Twitter", "appType": 0, "versionName": "8.76.0-release.01", "packageX": "com.twitter.android", "versionCode": "8.76.0-release.01"}, {"inTime": 1771728645948, "upTime": 1774305220865, "appName": "UATAS", "appType": 0, "versionName": "2.8.71", "packageX": "com.uatas.android", "versionCode": "2.8.71"}, {"inTime": 1764914786200, "upTime": 1769901097639, "appName": "Video Player", "appType": 0, "versionName": "1.1.8", "packageX": "com.vault.player.easyvideodownloader", "versionCode": "1.1.8"}, {"inTime": 1750316087148, "upTime": 1775689547062, "appName": "WhatsApp", "appType": 0, "versionName": "2.26.13.73", "packageX": "com.whatsapp", "versionCode": "2.26.13.73"}, {"inTime": 1764258917678, "upTime": 1775858938780, "appName": "Hypic", "appType": 0, "versionName": "8.5.0", "packageX": "com.xt.retouchoversea", "versionCode": "8.5.0"}, {"inTime": 1750315554997, "upTime": 1775166118488, "appName": "My Home Credit Indonesia", "appType": 0, "versionName": "3.93", "packageX": "id.co.myhomecredit", "versionCode": "3.93"}, {"inTime": 1767242407690, "upTime": 1775858859689, "appName": "DANA", "appType": 0, "versionName": "2.120.1", "packageX": "id.dana", "versionCode": "2.120.1"}, {"inTime": 1772368419437, "upTime": 1775166206319, "appName": "Akulaku", "appType": 0, "versionName": "5.4.30", "packageX": "io.silvrr.installment", "versionCode": "5.4.30"}, {"inTime": 1750315542677, "upTime": 1774305359195, "appName": "m.tix - XXI", "appType": 0, "versionName": "9.2.0", "packageX": "lds.cinema21", "versionCode": "9.2.0"}, {"inTime": 1750316006106, "upTime": 1775519269599, "appName": "Telegram", "appType": 0, "versionName": "12.6.4", "packageX": "org.telegram.messenger", "versionCode": "12.6.4"}, {"inTime": 1750315586582, "upTime": 1775091102704, "appName": "Omi", "appType": 0, "versionName": "7.50.0", "packageX": "sg.omi", "versionCode": "7.50.0"}, {"inTime": 1763381378407, "upTime": 1775858882031, "appName": "inDrive", "appType": 0, "versionName": "5.163.0", "packageX": "sinet.startup.inDriver", "versionCode": "5.163.0"}, {"inTime": 1757772107187, "upTime": 1757772107187, "appName": "Sticker Maker for WhatsApp - WAsticker", "appType": 0, "versionName": "928", "packageX": "stickerwhatsapp.com.stickers", "versionCode": "928"}, {"inTime": 1768653429570, "upTime": 1775689839151, "appName": "Marble Crush", "appType": 0, "versionName": "3.2", "packageX": "zuma.deluxe.marble.crush.match.free", "versionCode": "3.2"}], "smsList": [], "feature": {"feature_1": 1, "feature_2": 1, "feature_3": 1, "feature_4": 1, "feature_5": 1, "feature_6": 1, "feature_7": 1, "feature_8": 1, "feature_9": 1, "feature_10": 1, "feature_11": 1, "feature_12": 1, "feature_13": 1, "feature_14": 1, "feature_15": 1, "feature_16": 1, "feature_17": 1, "feature_18": 1, "feature_19": 1, "feature_20": 1, "feature_21": 1, "feature_22": 1, "feature_23": 1, "feature_24": 1, "feature_25": 0, "feature_26": 0, "feature_27": 0, "feature_28": 0, "feature_29": 0, "feature_30": 0, "feature_31": 1, "feature_32": 1, "feature_33": 1, "feature_34": 1, "feature_35": 1, "feature_36": 1, "feature_37": 1, "feature_38": 1, "feature_39": 1, "feature_40": 1, "feature_41": 1, "feature_42": 1, "feature_43": 1, "feature_44": 1, "feature_45": 1, "feature_46": 1, "feature_47": 1, "feature_48": 1, "feature_49": 1, "feature_50": 1, "feature_51": 1, "feature_52": 1, "feature_53": 1, "feature_54": 1, "feature_55": 1, "feature_56": 1, "feature_57": 1, "feature_58": 1, "feature_59": 1, "feature_60": 1, "feature_61": 1, "feature_62": 1, "feature_63": 1, "feature_64": 1, "feature_65": 1, "feature_66": 1, "feature_67": 1, "feature_68": 1, "feature_69": 1, "feature_70": 1, "feature_71": 1, "feature_72": 1, "feature_73": 1, "feature_74": 1, "feature_75": 1, "feature_76": 1, "feature_77": 1, "feature_78": 1, "feature_79": 0, "feature_80": 0, "feature_81": 1, "feature_82": 1, "feature_83": 1, "feature_84": 1, "feature_85": 1, "feature_86": 1, "feature_87": 1, "feature_88": 1, "feature_89": 1, "feature_90": 1, "feature_91": 1, "feature_92": 1, "feature_93": 1, "feature_94": 1, "feature_95": 1, "feature_96": 1, "feature_97": 1, "feature_98": 1, "feature_99": 1, "feature_100": 1, "feature_101": 1, "feature_102": 1, "feature_103": 1, "feature_104": 1, "feature_105": 0, "feature_106": 0, "feature_107": 0, "feature_108": 0, "feature_109": 0, "feature_110": 0, "feature_111": 0, "feature_112": 0, "feature_113": 0, "feature_114": 0, "feature_115": 0, "feature_116": 0, "feature_117": 0, "feature_118": 0, "feature_119": 0, "feature_120": 0, "feature_121": 0, "feature_122": 9, "0317_card_other_phone_count": 0, "0317_card_other_device_count": 0, "0317_card_other_idcard_count": 0, "0317_idcard_other_card_count": 0, "0317_idcard_other_device_count": 0, "0317_idcard_other_phone_count": 0, "0317_device_other_card_count": 0, "0317_device_other_idcard_count": 0, "0317_device_other_phone_count": 0, "0119_other_app_max_overdue_day": 0, "feature_123": 1, "feature_sms_cnt_less_10": 1, "feature_124": 0, "feature_cur_money_all": 0, "feature_cur_money_all_add_order": 500000, "feature_cur_money_app_add_order": 500000, "cnt_phone_60_all_clear_order": 0, "feature_1888": 0, "feature_2197": 0, "feature_2506": 0, "feature_2815": 0, "app_phone_loansprogress": 0, "app_ID_loansprogress": 0, "app_bank_loansprogress": 0, "app_gaid_loansprogress": 0, "app_phone_overdue": 0, "app_ID_overdue": 0, "app_bank_overdue": 0, "app_gaid_overdue": 0, "app_90_phone_loansprogress": 0, "current_loan_cnt_30d": 0, "current_loan_cnt_60d": 0, "current_loan_cnt_90d": 0, "app_90_ID_loansprogress": 0, "app_90_bank_loansprogress": 0, "app_90_gaid_loansprogress": 0, "app_90_phone_overdue": 0, "app_90_ID_overdue": 0, "app_90_bank_overdue": 0, "app_90_gaid_overdue": 0, "id_90_app_max_overdue_day": 0, "id_90_product_max_overdue_day": 0, "id_90_all_max_overdue_day": 0, "phone_90_app_max_overdue_day": 0, "phone_90_product_max_overdue_day": 0, "phone_90_all_max_overdue_day": 0, "bank_90_app_max_overdue_day": 0, "bank_90_product_max_overdue_day": 0, "bank_90_all_max_overdue_day": 0, "gaid_90_app_max_overdue_day": 0, "gaid_90_product_max_overdue_day": 0, "gaid_90_all_max_overdue_day": 0, "id_90_all_payout_cnt": 0, "phone_90_all_payout_cnt": 0, "bank_90_all_payout_cnt": 0, "gaid_90_all_payout_cnt": 0, "user_order_age": 0, "phone_app_1_early_repay_2_cnt": 0, "phone_app_3_early_repay_2_cnt": 0, "phone_app_5_early_repay_2_cnt": 0, "phone_app_7_early_repay_2_cnt": 0, "this_to_last_order_apply_time": -999, "has_other_app_loan": 0, "other_app_loan_cnt": 0, "other_app_loan_cnt_30d": 0, "other_app_loan_cnt_60d": 0, "other_app_loan_cnt_90d": 0, "other_app_repay_cnt": 0, "other_app_repay_cnt_30d": 0, "other_app_repay_cnt_60d": 0, "other_app_repay_cnt_90d": 0, "has_other_app_overdue": 0, "has_other_app_apply": 0, "all_user_order_age": -999, "other_app_last_settle_amt": 0, "other_app_last_settle_days": 0, "first_loan_repay_money": 0, "same_as_reg_ip_30_cnt": 0, "is_reg_ip_used_by_other": 0, "main_credit_ascore_v5_and": 465, "V504": 311, "main_credit_ascore_v8_noapp": 537, "sub_fdc_loan_ascore_v4": 603, "cashloan_lst30_cnt": 6, "main_credit_ascore_v9_uneven": 417, "main_credit_ascore_v8_app": 544, "main_credit_ascore_v6_app_fdc": 568, "main_credit_ascore_v5_ios": 360, "age_ktp": 31, "risk_grade_l1_v6_2": "F", "main_credit_ascore_v6_app_notfdc": 603, "V287": 30, "phone_OJK_90d": 8, "main_credit_ascore_v9_loan_slider": 561, "fdc_rupiahcepat_trans_amt_max": 100, "0617_battery_status": 0, "0119_battery_is_charging": 0, "0119_battery_pct": 70, "0314_is_using_proxy_port": 0, "0314_is_using_vpn": 0, "0314_is_simulator": 0, "0314_build_name": "1.0", "0126_is_in_black": 0, "0126_is_in_indo_order": 1, "0201_is_in_indo_tele": 0, "0316_tele_to_apply_day": -999}, "FDC": {"history_inquiry": {"statistic": {"3_hari": 6, "7_hari": 8, "30_hari": 10, "90_hari": 13, "180_hari": 13, "360_hari": 16, ">360_hari": 30}, "last3DaysInquiry": [{"tgl_inquiry": "2026-04-13 06:16:11", "jml_data": 18, "hit_by": "KLIKUMKM"}, {"tgl_inquiry": "2026-04-13 10:53:02", "jml_data": 18, "hit_by": "KTAKILAT"}, {"tgl_inquiry": "2026-04-12 11:37:06", "jml_data": 18, "hit_by": "SOLUSIKU"}, {"tgl_inquiry": "2026-04-12 13:38:01", "jml_data": 18, "hit_by": "KREDITO"}, {"tgl_inquiry": "2026-04-12 13:39:50", "jml_data": 18, "hit_by": "CAIRIN"}, {"tgl_inquiry": "2026-04-12 19:58:03", "jml_data": 18, "hit_by": "SINGA"}, {"tgl_inquiry": "2026-04-11 16:09:09", "jml_data": 18, "hit_by": "BANTUSAKU"}, {"tgl_inquiry": "2026-04-12 20:09:58", "jml_data": 18, "hit_by": "INDOSAKU"}]}, "pinjaman": [{"id_penyelenggara": "AFDC148", "jenis_pengguna": 1, "nama_borrower": "ELISAH", "no_identitas": "3507056901950004", "no_npwp": "", "no_hp": "6281*****2469", "email": "eli****021@gmail.com", "tgl_perjanjian_borrower": "2026-04-08", "tgl_penyaluran_dana": "2026-04-08", "nilai_pendanaan": 780000, "tgl_pelaporan_data": "2026-04-11", "sisa_pinjaman_berjalan": 780000, "tgl_jatuh_tempo_pinjaman": "2026-09-05", "kualitas_pinjaman": "1", "dpd_terakhir": 0, "dpd_max": 0, "status_pinjaman": "O", "jenis_pengguna_ket": "Individual", "kualitas_pinjaman_ket": "Lancar", "status_pinjaman_ket": "Outstanding", "penyelesaian_w_oleh": "Default", "pendanaan_syariah": false, "tipe_pinjaman": "Multiguna", "sub_tipe_pinjaman": "Paylater/ Line Of Credit", "reference": "", "id": "8f58e20d4b57d0dc0d2882f36e4be1ac", "agunan": "Tidak Memiliki Agunan", "tgl_agunan": "", "nama_penjamin": "", "no_agunan": "", "pendapatan": 3000000}, {"id_penyelenggara": "AFDC123", "jenis_pengguna": 1, "nama_borrower": "ELISAH", "no_identitas": "3507056901950004", "no_npwp": "", "no_hp": "6281*****2469", "email": "eli****995@gmail.com", "tgl_perjanjian_borrower": "2026-03-31", "tgl_penyaluran_dana": "2026-03-31", "nilai_pendanaan": 800000, "tgl_pelaporan_data": "2026-04-11", "sisa_pinjaman_berjalan": 800000, "tgl_jatuh_tempo_pinjaman": "2026-05-31", "kualitas_pinjaman": "1", "dpd_terakhir": 0, "dpd_max": 0, "status_pinjaman": "O", "jenis_pengguna_ket": "Individual", "kualitas_pinjaman_ket": "Lancar", "status_pinjaman_ket": "Outstanding", "penyelesaian_w_oleh": "Default", "pendanaan_syariah": false, "tipe_pinjaman": "Multiguna", "sub_tipe_pinjaman": "Onetime Loan / Cash Loan", "reference": "", "id": "eb302bca9ea87b359d41bbe9f4c843d4", "agunan": "Tidak Memiliki Agunan", "tgl_agunan": "", "nama_penjamin": "", "no_agunan": "", "pendapatan": 3000000}, {"id_penyelenggara": "AFDC243", "jenis_pengguna": 1, "nama_borrower": "ELISAH", "no_identitas": "3507056901950004", "no_npwp": "", "no_hp": "6281*****2469", "email": "eli****021@gmail.com", "tgl_perjanjian_borrower": "2026-03-13", "tgl_penyaluran_dana": "2026-03-13", "nilai_pendanaan": 300000, "tgl_pelaporan_data": "2026-03-31", "sisa_pinjaman_berjalan": 0, "tgl_jatuh_tempo_pinjaman": "2026-04-12", "kualitas_pinjaman": "1", "dpd_terakhir": 0, "dpd_max": 0, "status_pinjaman": "L", "jenis_pengguna_ket": "Individual", "kualitas_pinjaman_ket": "Lancar", "status_pinjaman_ket": "Fully Paid", "penyelesaian_w_oleh": "Default", "pendanaan_syariah": false, "tipe_pinjaman": "Multiguna", "sub_tipe_pinjaman": "Onetime Loan / Cash Loan", "reference": "", "id": "3058a89c3537d076306c385276671aed", "agunan": "Tidak Memiliki Agunan", "tgl_agunan": "", "nama_penjamin": "", "no_agunan": "", "pendapatan": 0}, {"id_penyelenggara": "AFDC233", "jenis_pengguna": 1, "nama_borrower": "ELISAH", "no_identitas": "3507056901950004", "no_npwp": "", "no_hp": "6281*****2469", "email": "eli****021@gmail.com", "tgl_perjanjian_borrower": "2026-02-16", "tgl_penyaluran_dana": "2026-02-16", "nilai_pendanaan": 200000, "tgl_pelaporan_data": "2026-02-28", "sisa_pinjaman_berjalan": 0, "tgl_jatuh_tempo_pinjaman": "2026-03-16", "kualitas_pinjaman": "1", "dpd_terakhir": 0, "dpd_max": 0, "status_pinjaman": "L", "jenis_pengguna_ket": "Individual", "kualitas_pinjaman_ket": "Lancar", "status_pinjaman_ket": "Fully Paid", "penyelesaian_w_oleh": "Default", "pendanaan_syariah": false, "tipe_pinjaman": "Multiguna", "sub_tipe_pinjaman": "Onetime Loan / Cash Loan", "reference": "", "id": "e0a106934d5b1475a1122f883a08b646", "agunan": "Tidak Memiliki Agunan", "tgl_agunan": "", "nama_penjamin": "", "no_agunan": "", "pendapatan": 2500000}, {"id_penyelenggara": "AFDC123", "jenis_pengguna": 1, "nama_borrower": "ELISAH", "no_identitas": "3507056901950004", "no_npwp": "", "no_hp": "6281*****2469", "email": "eli****995@gmail.com", "tgl_perjanjian_borrower": "2026-02-03", "tgl_penyaluran_dana": "2026-02-03", "nilai_pendanaan": 1000000, "tgl_pelaporan_data": "2026-04-04", "sisa_pinjaman_berjalan": 0, "tgl_jatuh_tempo_pinjaman": "2026-04-03", "kualitas_pinjaman": "1", "dpd_terakhir": 0, "dpd_max": 0, "status_pinjaman": "L", "jenis_pengguna_ket": "Individual", "kualitas_pinjaman_ket": "Lancar", "status_pinjaman_ket": "Fully Paid", "penyelesaian_w_oleh": "Default", "pendanaan_syariah": false, "tipe_pinjaman": "Multiguna", "sub_tipe_pinjaman": "Onetime Loan / Cash Loan", "reference": "", "id": "e1a027ff1af8df9cb34bf0a0e94ef924", "agunan": "Tidak Memiliki Agunan", "tgl_agunan": "", "nama_penjamin": "", "no_agunan": "", "pendapatan": 3000000}, {"id_penyelenggara": "AFDC184", "jenis_pengguna": 1, "nama_borrower": "ELISAH", "no_identitas": "3507056901950004", "no_npwp": "", "no_hp": "6281*****2469", "email": "eli****021@gmail.com", "tgl_perjanjian_borrower": "2024-06-25", "tgl_penyaluran_dana": "2024-06-25", "nilai_pendanaan": 500000, "tgl_pelaporan_data": "2024-11-17", "sisa_pinjaman_berjalan": 0, "tgl_jatuh_tempo_pinjaman": "2024-10-03", "kualitas_pinjaman": "3", "dpd_terakhir": 43, "dpd_max": 43, "status_pinjaman": "W", "jenis_pengguna_ket": "Individual", "kualitas_pinjaman_ket": "Kurang Lancar", "status_pinjaman_ket": "Write-Off", "penyelesaian_w_oleh": "Default", "pendanaan_syariah": false, "tipe_pinjaman": "Multiguna", "sub_tipe_pinjaman": "Onetime Loan / Cash Loan", "reference": "", "id": "d1238965ae11a51f0918f82479d50c74", "agunan": "Tidak Memiliki Agunan", "tgl_agunan": "", "nama_penjamin": "", "no_agunan": "", "pendapatan": 3000000}, {"id_penyelenggara": "AFDC238", "jenis_pengguna": 1, "nama_borrower": "ELISAH", "no_identitas": "3507056901950004", "no_npwp": "", "no_hp": "6281*****2469", "email": "eli****021@gmail.com", "tgl_perjanjian_borrower": "2024-06-15", "tgl_penyaluran_dana": "2024-06-15", "nilai_pendanaan": 1000000, "tgl_pelaporan_data": "2024-12-17", "sisa_pinjaman_berjalan": 1000000, "tgl_jatuh_tempo_pinjaman": "2024-09-17", "kualitas_pinjaman": "5", "dpd_terakhir": 91, "dpd_max": 171, "status_pinjaman": "W", "jenis_pengguna_ket": "Individual", "kualitas_pinjaman_ket": "Macet", "status_pinjaman_ket": "Write-Off", "penyelesaian_w_oleh": "Default", "pendanaan_syariah": false, "tipe_pinjaman": "Multiguna", "sub_tipe_pinjaman": "Onetime Loan / Cash Loan", "reference": "", "id": "1c85a727162d85b361d1a3706253b282", "agunan": "Tidak Memiliki Agunan", "tgl_agunan": "", "nama_penjamin": "", "no_agunan": "", "pendapatan": 3000000}, {"id_penyelenggara": "AFDC230", "jenis_pengguna": 1, "nama_borrower": "ELISAH", "no_identitas": "3507056901950004", "no_npwp": "000000000000000", "no_hp": "6281*****2469", "email": "eli****021@gmail.com", "tgl_perjanjian_borrower": "2024-03-24", "tgl_penyaluran_dana": "2024-03-24", "nilai_pendanaan": 1200000, "tgl_pelaporan_data": "2024-06-16", "sisa_pinjaman_berjalan": 0, "tgl_jatuh_tempo_pinjaman": "2024-06-24", "kualitas_pinjaman": "1", "dpd_terakhir": 0, "dpd_max": 0, "status_pinjaman": "L", "jenis_pengguna_ket": "Individual", "kualitas_pinjaman_ket": "Lancar", "status_pinjaman_ket": "Fully Paid", "penyelesaian_w_oleh": "Default", "pendanaan_syariah": false, "tipe_pinjaman": "Multiguna", "sub_tipe_pinjaman": "Onetime Loan / Cash Loan", "reference": "", "id": "8004db69af3e9c6b0e1b5266a15d21b5", "agunan": "Tidak Memiliki Agunan", "tgl_agunan": "", "nama_penjamin": "", "no_agunan": "", "pendapatan": 0}, {"id_penyelenggara": "AFDC239", "jenis_pengguna": 1, "nama_borrower": "ELISAH", "no_identitas": "3507056901950004", "no_npwp": "", "no_hp": "6281*****2469", "email": "628****469@easycash.id", "tgl_perjanjian_borrower": "2024-01-11", "tgl_penyaluran_dana": "2024-01-11", "nilai_pendanaan": 2100000, "tgl_pelaporan_data": "2024-03-09", "sisa_pinjaman_berjalan": 0, "tgl_jatuh_tempo_pinjaman": "2024-04-10", "kualitas_pinjaman": "1", "dpd_terakhir": 0, "dpd_max": 14, "status_pinjaman": "L", "jenis_pengguna_ket": "Individual", "kualitas_pinjaman_ket": "Lancar", "status_pinjaman_ket": "Fully Paid", "penyelesaian_w_oleh": "Default", "pendanaan_syariah": false, "tipe_pinjaman": "Multiguna", "sub_tipe_pinjaman": "Onetime Loan / Cash Loan", "reference": "", "id": "dd69f09d7549e6f657180c0ed8e01a3d", "agunan": "Tidak Memiliki Agunan", "tgl_agunan": "", "nama_penjamin": "", "no_agunan": "", "pendapatan": 0}, {"id_penyelenggara": "AFDC239", "jenis_pengguna": 1, "nama_borrower": "ELISAH", "no_identitas": "3507056901950004", "no_npwp": "", "no_hp": "6281*****2469", "email": "628****469@easycash.id", "tgl_perjanjian_borrower": "2024-01-11", "tgl_penyaluran_dana": "2024-01-11", "nilai_pendanaan": 350000, "tgl_pelaporan_data": "2024-06-10", "sisa_pinjaman_berjalan": 350000, "tgl_jatuh_tempo_pinjaman": "2024-03-11", "kualitas_pinjaman": "5", "dpd_terakhir": 92, "dpd_max": 92, "status_pinjaman": "W", "jenis_pengguna_ket": "Individual", "kualitas_pinjaman_ket": "Macet", "status_pinjaman_ket": "Write-Off", "penyelesaian_w_oleh": "Insurance", "pendanaan_syariah": false, "tipe_pinjaman": "Multiguna", "sub_tipe_pinjaman": "Onetime Loan / Cash Loan", "reference": "", "id": "c2e7625a5ade804871ea8c5e610a7c96", "agunan": "Tidak Memiliki Agunan", "tgl_agunan": "", "nama_penjamin": "", "no_agunan": "", "pendapatan": 0}, {"id_penyelenggara": "AFDC239", "jenis_pengguna": 1, "nama_borrower": "ELISAH", "no_identitas": "3507056901950004", "no_npwp": "", "no_hp": "6281*****2469", "email": "628****469@easycash.id", "tgl_perjanjian_borrower": "2024-01-11", "tgl_penyaluran_dana": "2024-01-11", "nilai_pendanaan": 350000, "tgl_pelaporan_data": "2024-06-10", "sisa_pinjaman_berjalan": 350000, "tgl_jatuh_tempo_pinjaman": "2024-03-26", "kualitas_pinjaman": "4", "dpd_terakhir": 77, "dpd_max": 77, "status_pinjaman": "W", "jenis_pengguna_ket": "Individual", "kualitas_pinjaman_ket": "Diragukan", "status_pinjaman_ket": "Write-Off", "penyelesaian_w_oleh": "Insurance", "pendanaan_syariah": false, "tipe_pinjaman": "Multiguna", "sub_tipe_pinjaman": "Onetime Loan / Cash Loan", "reference": "", "id": "2030268569459b8ef9b72350610b8dc7", "agunan": "Tidak Memiliki Agunan", "tgl_agunan": "", "nama_penjamin": "", "no_agunan": "", "pendapatan": 0}, {"id_penyelenggara": "AFDC239", "jenis_pengguna": 1, "nama_borrower": "ELISAH", "no_identitas": "3507056901950004", "no_npwp": "", "no_hp": "6281*****2469", "email": "628****469@easycash.id", "tgl_perjanjian_borrower": "2024-01-11", "tgl_penyaluran_dana": "2024-01-11", "nilai_pendanaan": 350000, "tgl_pelaporan_data": "2024-04-26", "sisa_pinjaman_berjalan": 350000, "tgl_jatuh_tempo_pinjaman": "2024-02-25", "kualitas_pinjaman": "4", "dpd_terakhir": 62, "dpd_max": 62, "status_pinjaman": "F", "jenis_pengguna_ket": "Individual", "kualitas_pinjaman_ket": "Diragukan", "status_pinjaman_ket": "Full Payment", "penyelesaian_w_oleh": "Desk Collection", "pendanaan_syariah": false, "tipe_pinjaman": "Multiguna", "sub_tipe_pinjaman": "Onetime Loan / Cash Loan", "reference": "7b199dbfa2c96af7778d7fa0134117bd", "id": "3e070aa96829d452eb1040c55222bb06", "agunan": "Tidak Memiliki Agunan", "tgl_agunan": "", "nama_penjamin": "", "no_agunan": "", "pendapatan": 0}, {"id_penyelenggara": "AFDC239", "jenis_pengguna": 1, "nama_borrower": "ELISAH", "no_identitas": "3507056901950004", "no_npwp": "", "no_hp": "6281*****2469", "email": "628****469@easycash.id", "tgl_perjanjian_borrower": "2024-01-11", "tgl_penyaluran_dana": "2024-01-11", "nilai_pendanaan": 350000, "tgl_pelaporan_data": "2024-06-09", "sisa_pinjaman_berjalan": 350000, "tgl_jatuh_tempo_pinjaman": "2024-04-10", "kualitas_pinjaman": "4", "dpd_terakhir": 61, "dpd_max": 61, "status_pinjaman": "W", "jenis_pengguna_ket": "Individual", "kualitas_pinjaman_ket": "Diragukan", "status_pinjaman_ket": "Write-Off", "penyelesaian_w_oleh": "Insurance", "pendanaan_syariah": false, "tipe_pinjaman": "Multiguna", "sub_tipe_pinjaman": "Onetime Loan / Cash Loan", "reference": "", "id": "4a1f1adb25037fa0f2c25314d47a3473", "agunan": "Tidak Memiliki Agunan", "tgl_agunan": "", "nama_penjamin": "", "no_agunan": "", "pendapatan": 0}, {"id_penyelenggara": "AFDC239", "jenis_pengguna": 1, "nama_borrower": "ELISAH", "no_identitas": "3507056901950004", "no_npwp": "", "no_hp": "6281*****2469", "email": "628****469@easycash.id", "tgl_perjanjian_borrower": "2024-01-11", "tgl_penyaluran_dana": "2024-01-11", "nilai_pendanaan": 350000, "tgl_pelaporan_data": "2024-05-11", "sisa_pinjaman_berjalan": 350000, "tgl_jatuh_tempo_pinjaman": "2024-03-11", "kualitas_pinjaman": "4", "dpd_terakhir": 62, "dpd_max": 62, "status_pinjaman": "F", "jenis_pengguna_ket": "Individual", "kualitas_pinjaman_ket": "Diragukan", "status_pinjaman_ket": "Full Payment", "penyelesaian_w_oleh": "Desk Collection", "pendanaan_syariah": false, "tipe_pinjaman": "Multiguna", "sub_tipe_pinjaman": "Onetime Loan / Cash Loan", "reference": "c2e7625a5ade804871ea8c5e610a7c96", "id": "5385d7a6746929d28615aa808ace1a42", "agunan": "Tidak Memiliki Agunan", "tgl_agunan": "", "nama_penjamin": "", "no_agunan": "", "pendapatan": 0}, {"id_penyelenggara": "AFDC239", "jenis_pengguna": 1, "nama_borrower": "ELISAH", "no_identitas": "3507056901950004", "no_npwp": "", "no_hp": "6281*****2469", "email": "628****469@easycash.id", "tgl_perjanjian_borrower": "2024-01-11", "tgl_penyaluran_dana": "2024-01-11", "nilai_pendanaan": 350000, "tgl_pelaporan_data": "2024-06-10", "sisa_pinjaman_berjalan": 350000, "tgl_jatuh_tempo_pinjaman": "2024-04-10", "kualitas_pinjaman": "4", "dpd_terakhir": 62, "dpd_max": 62, "status_pinjaman": "F", "jenis_pengguna_ket": "Individual", "kualitas_pinjaman_ket": "Diragukan", "status_pinjaman_ket": "Full Payment", "penyelesaian_w_oleh": "Desk Collection", "pendanaan_syariah": false, "tipe_pinjaman": "Multiguna", "sub_tipe_pinjaman": "Onetime Loan / Cash Loan", "reference": "4a1f1adb25037fa0f2c25314d47a3473", "id": "65ab3102507ed8b3f3973ceb87f50042", "agunan": "Tidak Memiliki Agunan", "tgl_agunan": "", "nama_penjamin": "", "no_agunan": "", "pendapatan": 0}, {"id_penyelenggara": "AFDC239", "jenis_pengguna": 1, "nama_borrower": "ELISAH", "no_identitas": "3507056901950004", "no_npwp": "", "no_hp": "6281*****2469", "email": "628****469@easycash.id", "tgl_perjanjian_borrower": "2024-01-11", "tgl_penyaluran_dana": "2024-01-11", "nilai_pendanaan": 350000, "tgl_pelaporan_data": "2024-05-26", "sisa_pinjaman_berjalan": 350000, "tgl_jatuh_tempo_pinjaman": "2024-03-26", "kualitas_pinjaman": "4", "dpd_terakhir": 62, "dpd_max": 62, "status_pinjaman": "F", "jenis_pengguna_ket": "Individual", "kualitas_pinjaman_ket": "Diragukan", "status_pinjaman_ket": "Full Payment", "penyelesaian_w_oleh": "Desk Collection", "pendanaan_syariah": false, "tipe_pinjaman": "Multiguna", "sub_tipe_pinjaman": "Onetime Loan / Cash Loan", "reference": "2030268569459b8ef9b72350610b8dc7", "id": "6e0dab1f6db476f768e7dfd948828291", "agunan": "Tidak Memiliki Agunan", "tgl_agunan": "", "nama_penjamin": "", "no_agunan": "", "pendapatan": 0}, {"id_penyelenggara": "AFDC239", "jenis_pengguna": 1, "nama_borrower": "ELISAH", "no_identitas": "3507056901950004", "no_npwp": "", "no_hp": "6281*****2469", "email": "628****469@easycash.id", "tgl_perjanjian_borrower": "2024-01-11", "tgl_penyaluran_dana": "2024-01-11", "nilai_pendanaan": 350000, "tgl_pelaporan_data": "2024-06-10", "sisa_pinjaman_berjalan": 350000, "tgl_jatuh_tempo_pinjaman": "2024-02-25", "kualitas_pinjaman": "5", "dpd_terakhir": 107, "dpd_max": 107, "status_pinjaman": "W", "jenis_pengguna_ket": "Individual", "kualitas_pinjaman_ket": "Macet", "status_pinjaman_ket": "Write-Off", "penyelesaian_w_oleh": "Insurance", "pendanaan_syariah": false, "tipe_pinjaman": "Multiguna", "sub_tipe_pinjaman": "Onetime Loan / Cash Loan", "reference": "", "id": "7b199dbfa2c96af7778d7fa0134117bd", "agunan": "Tidak Memiliki Agunan", "tgl_agunan": "", "nama_penjamin": "", "no_agunan": "", "pendapatan": 0}, {"id_penyelenggara": "AFDC239", "jenis_pengguna": 1, "nama_borrower": "ELISAH", "no_identitas": "3507056901950004", "no_npwp": "", "no_hp": "6281*****2469", "email": "628****469@easycash.id", "tgl_perjanjian_borrower": "2023-11-15", "tgl_penyaluran_dana": "2023-11-15", "nilai_pendanaan": 500000, "tgl_pelaporan_data": "2024-01-11", "sisa_pinjaman_berjalan": 0, "tgl_jatuh_tempo_pinjaman": "2024-01-14", "kualitas_pinjaman": "1", "dpd_terakhir": 0, "dpd_max": 0, "status_pinjaman": "L", "jenis_pengguna_ket": "Individual", "kualitas_pinjaman_ket": "Lancar", "status_pinjaman_ket": "Fully Paid", "penyelesaian_w_oleh": "Default", "pendanaan_syariah": false, "tipe_pinjaman": "Multiguna", "sub_tipe_pinjaman": "Onetime Loan / Cash Loan", "reference": "", "id": "b9897d4d696de0d6f20405208709a664", "agunan": "Tidak Memiliki Agunan", "tgl_agunan": "", "nama_penjamin": "", "no_agunan": "", "pendapatan": 0}], "platform_aktif": {"jumlahPlatformAktif": 2, "platform": ["AFDC148", "AFDC123"]}}, "Indo_XD_score": -999}}