{"country": "INDO", "eventType": "Indo_new_0115", "orderId": "id002kirw202602270715406793894", "applyTime": 1772151369000, "params": {"base": {"appname": "flex-rupiah", "newCustomer": 1, "birthday": "14-03-1985", "job": "", "channel": "未知渠道", "applyTime": 1772151369000, "gender": 1, "phone": "+6282138619401", "gaid": "a0803c63-2f2d-496d-a4c8-da9a6fc87f30", "bankCard": "901353250838", "idCard": "3403071403850002", "marita": 2, "children": 0, "salary": 0, "workYears": 4, "state": 0, "relationship1": 2, "relationship2": 5, "use": 0, "uaClientType": "Android", "orderSource": "self", "userTg": "XJX_0", "packageName": "com.flex.rupiah.trusta.flexrupiah"}, "appList": [{"inTime": 1766027680029, "upTime": 1771649381092, "appName": "Lite", "appType": 0, "versionName": "499.0.0.9.106", "packageX": "com.facebook.lite", "versionCode": "499.0.0.9.106"}, {"inTime": 1771933714188, "upTime": 1771933714188, "appName": "Asisten Pinjaman", "appType": 0, "versionName": "1.0.2", "packageX": "com.flex.rupiah.trusta.flexrupiah", "versionCode": "1.0.2"}, {"inTime": 1731586781706, "upTime": 1771767175692, "appName": "TikTok", "appType": 0, "versionName": "43.9.3", "packageX": "com.ss.android.ugc.trill", "versionCode": "43.9.3"}, {"inTime": 1754330066492, "upTime": 1771649623683, "appName": "WhatsApp", "appType": 0, "versionName": "2.26.6.72", "packageX": "com.whatsapp", "versionCode": "2.26.6.72"}, {"inTime": 1771819944815, "upTime": 1771819944815, "appName": "SeaBank", "appType": 0, "versionName": "3.38.0", "packageX": "id.co.bankbkemobile.digitalbank", "versionCode": "3.38.0"}, {"inTime": 1771809687803, "upTime": 1771809687803, "appName": "BRImo", "appType": 0, "versionName": "2.93.0", "packageX": "id.co.bri.brimo", "versionCode": "2.93.0"}, {"inTime": 1768598826084, "upTime": 1771499511045, "appName": "DANA", "appType": 0, "versionName": "2.114.1", "packageX": "id.dana", "versionCode": "2.114.1"}], "smsList": [], "FDC": {"history_inquiry": {"statistic": {"360_hari": 4, "30_hari": 1, ">360_hari": 24, "180_hari": 2, "3_hari": 0, "7_hari": 1, "90_hari": 1}, "last3DaysInquiry": [{"hit_by": "INDODANA", "jml_data": 4, "tgl_inquiry": "2026-02-23 09:01:35"}, {"hit_by": "KREDIFAZZ", "jml_data": 4, "tgl_inquiry": "2026-02-23 09:28:37"}, {"hit_by": "UKU", "jml_data": 4, "tgl_inquiry": "2026-02-23 17:50:18"}, {"hit_by": "FINPLUS", "jml_data": 4, "tgl_inquiry": "2026-02-23 09:42:50"}, {"hit_by": "UATAS", "jml_data": 4, "tgl_inquiry": "2026-02-23 15:32:52"}, {"hit_by": "SAMIR", "jml_data": 4, "tgl_inquiry": "2026-02-23 09:40:38"}, {"hit_by": "KREDITPINTAR", "jml_data": 4, "tgl_inquiry": "2026-02-23 16:35:33"}, {"hit_by": "RUPIAHCEPAT", "jml_data": 4, "tgl_inquiry": "2026-02-23 10:09:53"}, {"hit_by": "RUPIAHCEPAT", "jml_data": 4, "tgl_inquiry": "2026-02-23 10:01:08"}, {"hit_by": "PINJAMDUIT", "jml_data": 4, "tgl_inquiry": "2026-02-23 17:37:24"}, {"hit_by": "ADAKAMI", "jml_data": 0, "tgl_inquiry": "2026-02-23 15:24:28"}, {"hit_by": "ADAKAMI", "jml_data": 4, "tgl_inquiry": "2026-02-23 15:24:28"}, {"hit_by": "CAIRIN", "jml_data": 4, "tgl_inquiry": "2026-02-23 14:55:58"}, {"hit_by": "ADAPUNDI", "jml_data": 4, "tgl_inquiry": "2026-02-23 15:56:44"}, {"hit_by": "BANTUSAKU", "jml_data": 4, "tgl_inquiry": "2026-02-23 15:01:16"}]}, "pinjaman": [{"jenis_pengguna_ket": "Individual", "no_hp": "6282*****9401", "agunan": "Tidak Memiliki Agunan", "dpd_max": 0, "no_agunan": "", "tipe_pinjaman": "Multiguna", "reference": "", "pendapatan": 0, "tgl_jatuh_tempo_pinjaman": "2024-04-27", "dpd_terakhir": 0, "id": "6a9835b71a600836cabe2bd0433a4bd3", "id_penyelenggara": "AFDC243", "no_npwp": "", "sub_tipe_pinjaman": "Onetime Loan / Cash Loan", "email": "alv****oan@yahoo.com", "tgl_perjanjian_borrower": "2024-03-28", "nama_borrower": "KARYONO", "sisa_pinjaman_berjalan": 0, "jenis_pengguna": 1, "no_identitas": "3403071403850002", "tgl_penyaluran_dana": "2024-03-28", "kualitas_pinjaman": "1", "status_pinjaman_ket": "Fully Paid", "penyelesaian_w_oleh": "Default", "tgl_pelaporan_data": "2025-01-12", "nilai_pendanaan": 200000, "pendanaan_syariah": false, "kualitas_pinjaman_ket": "Lancar", "status_pinjaman": "L", "nama_penjamin": ""}, {"jenis_pengguna_ket": "Individual", "no_hp": "6282*****9401", "agunan": "Tidak Memiliki Agunan", "dpd_max": 10, "no_agunan": "", "tipe_pinjaman": "Multiguna", "reference": "", "pendapatan": 0, "tgl_jatuh_tempo_pinjaman": "2024-06-30", "dpd_terakhir": 0, "id": "caca4d3bb7174b6c6f1dc0bd3ef68731", "id_penyelenggara": "AFDC238", "sub_tipe_pinjaman": "Onetime Loan / Cash Loan", "email": "alv****oan@gmail.com", "tgl_perjanjian_borrower": "2024-03-28", "nama_borrower": "KARYONO", "sisa_pinjaman_berjalan": 0, "jenis_pengguna": 1, "no_identitas": "3403071403850002", "tgl_penyaluran_dana": "2024-03-28", "kualitas_pinjaman": "1", "status_pinjaman_ket": "Fully Paid", "penyelesaian_w_oleh": "Default", "tgl_pelaporan_data": "2024-07-01", "nilai_pendanaan": 1400000, "pendanaan_syariah": false, "kualitas_pinjaman_ket": "Lancar", "status_pinjaman": "L", "nama_penjamin": ""}, {"jenis_pengguna_ket": "Individual", "no_hp": "6282******2452", "agunan": "Tidak Memiliki Agunan", "dpd_max": 0, "no_agunan": "", "tipe_pinjaman": "Produktif", "reference": "", "pendapatan": 6000000, "tgl_jatuh_tempo_pinjaman": "2024-08-18", "dpd_terakhir": 0, "id": "12484ea650df755dbe39688fa458c7e1", "id_penyelenggara": "AFDC101", "no_npwp": "", "sub_tipe_pinjaman": "Invoice Financing", "email": "r2.****000@gmail.com", "tgl_perjanjian_borrower": "2022-10-25", "nama_borrower": "KARYONO", "sisa_pinjaman_berjalan": 0, "jenis_pengguna": 1, "no_identitas": "3403071403850002", "tgl_penyaluran_dana": "2023-12-18", "kualitas_pinjaman": "1", "status_pinjaman_ket": "Fully Paid", "penyelesaian_w_oleh": "Default", "tgl_pelaporan_data": "2026-01-12", "nilai_pendanaan": 5216355, "pendanaan_syariah": false, "kualitas_pinjaman_ket": "Lancar", "status_pinjaman": "L", "nama_penjamin": ""}, {"jenis_pengguna_ket": "Individual", "no_hp": "6282*****0452", "agunan": "Tidak Memiliki Agunan", "dpd_max": 3, "no_agunan": "", "tipe_pinjaman": "Produktif", "reference": "", "pendapatan": 0, "tgl_jatuh_tempo_pinjaman": "2023-10-25", "dpd_terakhir": 0, "id": "dd8009ba89840fc3f4026022797d7a8f", "id_penyelenggara": "AFDC101", "no_npwp": "", "sub_tipe_pinjaman": "Group-lending", "email": "r2.****522@bimafinance.com", "tgl_perjanjian_borrower": "2022-10-25", "nama_borrower": "KARYONO", "sisa_pinjaman_berjalan": 0, "jenis_pengguna": 1, "no_identitas": "3403071403850002", "tgl_penyaluran_dana": "2022-10-25", "kualitas_pinjaman": "1", "status_pinjaman_ket": "Fully Paid", "penyelesaian_w_oleh": "Default", "tgl_pelaporan_data": "2026-01-12", "nilai_pendanaan": 5647248, "pendanaan_syariah": false, "kualitas_pinjaman_ket": "Lancar", "status_pinjaman": "L", "nama_penjamin": ""}], "platform_aktif": {"jumlahPlatformAktif": 0, "platform": []}}, "feature": {"feature_1": 1, "feature_2": 1, "feature_3": 1, "feature_4": 1, "feature_5": 1, "feature_6": 1, "feature_7": 1, "feature_8": 1, "feature_9": 1, "feature_10": 1, "feature_11": 1, "feature_12": 1, "feature_13": 1, "feature_14": 1, "feature_15": 1, "feature_16": 1, "feature_17": 1, "feature_18": 1, "feature_19": 1, "feature_20": 1, "feature_21": 1, "feature_22": 1, "feature_23": 1, "feature_24": 1, "feature_25": 0, "feature_26": 0, "feature_27": 0, "feature_28": 0, "feature_29": 0, "feature_30": 0, "feature_31": 2, "feature_32": 2, "feature_33": 2, "feature_34": 2, "feature_35": 2, "feature_36": 2, "feature_37": 2, "feature_38": 2, "feature_39": 0, "feature_40": 0, "feature_41": 1, "feature_42": 1, "feature_43": 1, "feature_44": 1, "feature_45": 1, "feature_46": 1, "feature_47": 0, "feature_48": 0, "feature_49": 1, "feature_50": 1, "feature_51": 1, "feature_52": 1, "feature_53": 1, "feature_54": 1, "feature_55": 0, "feature_56": 0, "feature_57": 1, "feature_58": 1, "feature_59": 1, "feature_60": 1, "feature_61": 1, "feature_62": 1, "feature_63": 0, "feature_64": 0, "feature_65": 1, "feature_66": 1, "feature_67": 1, "feature_68": 1, "feature_69": 1, "feature_70": 1, "feature_71": 0, "feature_72": 0, "feature_73": 1, "feature_74": 1, "feature_75": 1, "feature_76": 1, "feature_77": 1, "feature_78": 1, "feature_79": 0, "feature_80": 0, "feature_81": 1, "feature_82": 1, "feature_83": 1, "feature_84": 1, "feature_85": 1, "feature_86": 1, "feature_87": 1, "feature_88": 1, "feature_89": 1, "feature_90": 1, "feature_91": 1, "feature_92": 1, "feature_93": 1, "feature_94": 1, "feature_95": 1, "feature_96": 1, "feature_97": 1, "feature_98": 1, "feature_99": 1, "feature_100": 1, "feature_101": 1, "feature_102": 1, "feature_103": 1, "feature_104": 1, "feature_105": 0, "feature_106": 0, "feature_107": 0, "feature_108": 0, "feature_109": 0, "feature_110": 0, "feature_111": 0, "feature_112": 0, "feature_113": 0, "feature_114": 0, "feature_115": 0, "feature_116": 0, "feature_117": 0, "feature_118": 0, "feature_119": 0, "feature_120": 0, "feature_121": 0, "feature_122": 3623, "0119_other_app_max_overdue_day": 0, "feature_123": 1, "feature_sms_cnt_less_10": 1, "feature_124": 0, "feature_cur_money_all": 0, "feature_cur_money_all_add_order": 600000, "feature_cur_money_app_add_order": 600000, "cnt_phone_60_all_clear_order": 0, "feature_1888": 0, "feature_2197": 0, "feature_2506": 0, "feature_2815": 0, "app_phone_loansprogress": 0, "app_ID_loansprogress": 0, "app_bank_loansprogress": 0, "app_gaid_loansprogress": 0, "app_phone_overdue": 0, "app_ID_overdue": 0, "app_bank_overdue": 0, "app_gaid_overdue": 0, "app_90_phone_loansprogress": 0, "app_90_ID_loansprogress": 0, "app_90_bank_loansprogress": 0, "app_90_gaid_loansprogress": 0, "app_90_phone_overdue": 0, "app_90_ID_overdue": 0, "app_90_bank_overdue": 0, "app_90_gaid_overdue": 0, "id_90_app_max_overdue_day": 0, "id_90_product_max_overdue_day": 0, "id_90_all_max_overdue_day": 0, "phone_90_app_max_overdue_day": 0, "phone_90_product_max_overdue_day": 0, "phone_90_all_max_overdue_day": 0, "bank_90_app_max_overdue_day": 0, "bank_90_product_max_overdue_day": 0, "bank_90_all_max_overdue_day": 0, "gaid_90_app_max_overdue_day": 0, "gaid_90_product_max_overdue_day": 0, "gaid_90_all_max_overdue_day": 0, "id_90_all_payout_cnt": 0, "phone_90_all_payout_cnt": 0, "bank_90_all_payout_cnt": 0, "gaid_90_all_payout_cnt": 0, "user_order_age": 0, "phone_app_1_early_repay_2_cnt": 0, "phone_app_3_early_repay_2_cnt": 0, "phone_app_5_early_repay_2_cnt": 0, "phone_app_7_early_repay_2_cnt": 0, "this_to_last_order_apply_time": 216335, "has_other_app_loan": 0, "has_other_app_overdue": 0, "has_other_app_apply": 0, "all_user_order_age": -999, "other_app_last_settle_amt": 0, "first_loan_repay_money": 0, "0617_battery_status": 0, "0119_battery_is_charging": 0, "0119_battery_pct": 43, "0126_is_in_black": 0, "0126_is_in_indo_order": 1, "0201_is_in_indo_tele": 1}}}