{"country": "INDO", "eventType": "Indo_new_0115", "orderId": "id002cpmb202603251719139078948", "applyTime": 1774434740000, "params": {"base": {"appname": "flex-rupiah", "newCustomer": 1, "birthday": "02-09-1974", "job": "12", "channel": "未知渠道", "applyTime": 1774434740000, "gender": 1, "phone": "+6281381134115", "gaid": "4bcb587c-f4c0-4115-beb4-f5078b5c8cb5", "bankCard": "1320015419097", "idCard": "3272010209740940", "marita": 2, "children": 0, "salary": 5000000, "workYears": 4, "state": 0, "relationship1": 4, "relationship2": 4, "use": 3, "uaClientType": "Android", "orderSource": "self", "userTg": "XJX_0", "packageName": "com.flex.rupiah.trusta.flexrupiah"}, "appList": [{"inTime": 1774375824964, "upTime": 1774375824964, "appName": "Singa", "appType": 0, "versionName": "3.0.6", "packageX": "com.asf.singa", "versionCode": "3.0.6"}, {"inTime": 1734079180953, "upTime": 1772254622765, "appName": "JMO", "appType": 0, "versionName": "4.15.19", "packageX": "com.bpjstku", "versionCode": "4.15.19"}, {"inTime": 53313947, "upTime": 53313947, "appName": "Clone Phone", "appType": 0, "versionName": "14.16.0", "packageX": "com.coloros.backuprestore", "versionCode": "14.16.0"}, {"inTime": 53314791, "upTime": 53314791, "appName": "Catatan", "appType": 0, "versionName": "15.3.42", "packageX": "com.coloros.note", "versionCode": "15.3.42"}, {"inTime": 53348139, "upTime": 53348139, "appName": "Kunci Layar", "appType": 0, "versionName": "15.0.2", "packageX": "com.coloros.onekeylockscreen", "versionCode": "15.0.2"}, {"inTime": 53309007, "upTime": 1774377944664, "appName": "Facebook", "appType": 0, "versionName": "553.0.0.56.58", "packageX": "com.facebook.katana", "versionCode": "553.0.0.56.58"}, {"inTime": 1737351291027, "upTime": 1773364657754, "appName": "Manajer File", "appType": 0, "versionName": "3.3.9", "packageX": "com.filemanager.managefile.fileexplorer.fileextractor", "versionCode": "3.3.9"}, {"inTime": 1774433868560, "upTime": 1774433868560, "appName": "Asisten Pinjaman", "appType": 0, "versionName": "1.0.3", "packageX": "com.flex.rupiah.trusta.flexrupiah", "versionCode": "1.0.3"}, {"inTime": 1764375656105, "upTime": 1764375656105, "appName": "MLBB777", "appType": 0, "versionName": "1.0.5", "packageX": "com.hsp.yn.mlbb777", "versionCode": "1.0.5"}, {"inTime": 1747017899840, "upTime": 1773447660183, "appName": "Rupiah Cepat", "appType": 0, "versionName": "3.7.1", "packageX": "com.loan.cash.credit.easy.kilat.cepat.pinjam.uang.dana.rupiah", "versionCode": "3.7.1"}, {"inTime": 53314279, "upTime": 1755191649067, "appName": "OPPO Saya", "appType": 0, "versionName": "EXP_8.60.2", "packageX": "com.oplus.member", "versionCode": "EXP_8.60.2"}, {"inTime": 1767743727301, "upTime": 1773772919384, "appName": "Shopee", "appType": 0, "versionName": "3.69.36", "packageX": "com.shopee.id", "versionCode": "3.69.36"}, {"inTime": 53342611, "upTime": 1773952850924, "appName": "Spotify", "appType": 0, "versionName": "9.1.32.2083", "packageX": "com.spotify.music", "versionCode": "9.1.32.2083"}, {"inTime": 1736037028863, "upTime": 1773951603417, "appName": "TikTok", "appType": 0, "versionName": "44.4.3", "packageX": "com.ss.android.ugc.trill", "versionCode": "44.4.3"}, {"inTime": 1735268959772, "upTime": 1773514306852, "appName": "MyTelkomsel", "appType": 0, "versionName": "9.1.0", "packageX": "com.telkomsel.telkomselcm", "versionCode": "9.1.0"}, {"inTime": 1758613865089, "upTime": 1773687220884, "appName": "WhatsApp", "appType": 0, "versionName": "2.26.10.72", "packageX": "com.whatsapp", "versionCode": "2.26.10.72"}, {"inTime": 1774363606136, "upTime": 1774363606136, "appName": "Adapundi", "appType": 0, "versionName": "4.5.7", "packageX": "com.yinshan.program.banda", "versionCode": "4.5.7"}, {"inTime": 1743723787675, "upTime": 1743723787675, "appName": "VPN Private", "appType": 0, "versionName": "2.0.14", "packageX": "free.vpn.private", "versionCode": "2.0.14"}, {"inTime": 1733078513123, "upTime": 1772463790873, "appName": "Livin' by Mandiri", "appType": 0, "versionName": "3.3.0", "packageX": "id.bmri.livin", "versionCode": "3.3.0"}, {"inTime": 1770387738629, "upTime": 1774329215869, "appName": "DANA", "appType": 0, "versionName": "2.119.0", "packageX": "id.dana", "versionCode": "2.119.0"}, {"inTime": 1763948616355, "upTime": 1763948616355, "appName": "SIAPkerja Lite", "appType": 0, "versionName": "1", "packageX": "org.chromium.webapk.a9e4a10f69063f88a_v2", "versionCode": "1"}], "smsList": [], "feature": {"feature_1": 1, "feature_2": 1, "feature_3": 1, "feature_4": 1, "feature_5": 1, "feature_6": 1, "feature_7": 1, "feature_8": 1, "feature_9": 1, "feature_10": 1, "feature_11": 1, "feature_12": 1, "feature_13": 1, "feature_14": 1, "feature_15": 1, "feature_16": 1, "feature_17": 1, "feature_18": 1, "feature_19": 1, "feature_20": 1, "feature_21": 1, "feature_22": 1, "feature_23": 1, "feature_24": 1, "feature_25": 0, "feature_26": 0, "feature_27": 0, "feature_28": 0, "feature_29": 0, "feature_30": 0, "feature_31": 1, "feature_32": 1, "feature_33": 1, "feature_34": 1, "feature_35": 1, "feature_36": 1, "feature_37": 1, "feature_38": 1, "feature_39": 1, "feature_40": 1, "feature_41": 1, "feature_42": 1, "feature_43": 1, "feature_44": 1, "feature_45": 1, "feature_46": 1, "feature_47": 1, "feature_48": 1, "feature_49": 1, "feature_50": 1, "feature_51": 1, "feature_52": 1, "feature_53": 1, "feature_54": 1, "feature_55": 1, "feature_56": 1, "feature_57": 1, "feature_58": 1, "feature_59": 1, "feature_60": 1, "feature_61": 1, "feature_62": 1, "feature_63": 1, "feature_64": 1, "feature_65": 1, "feature_66": 1, "feature_67": 1, "feature_68": 1, "feature_69": 1, "feature_70": 1, "feature_71": 1, "feature_72": 1, "feature_73": 1, "feature_74": 1, "feature_75": 1, "feature_76": 1, "feature_77": 1, "feature_78": 1, "feature_79": 0, "feature_80": 0, "feature_81": 1, "feature_82": 1, "feature_83": 1, "feature_84": 1, "feature_85": 1, "feature_86": 1, "feature_87": 1, "feature_88": 1, "feature_89": 1, "feature_90": 1, "feature_91": 1, "feature_92": 1, "feature_93": 1, "feature_94": 1, "feature_95": 1, "feature_96": 1, "feature_97": 1, "feature_98": 1, "feature_99": 1, "feature_100": 1, "feature_101": 1, "feature_102": 1, "feature_103": 1, "feature_104": 1, "feature_105": 0, "feature_106": 0, "feature_107": 0, "feature_108": 0, "feature_109": 0, "feature_110": 0, "feature_111": 0, "feature_112": 0, "feature_113": 0, "feature_114": 0, "feature_115": 0, "feature_116": 0, "feature_117": 0, "feature_118": 0, "feature_119": 0, "feature_120": 0, "feature_121": 0, "feature_122": 13, "0317_card_other_phone_count": 0, "0317_card_other_device_count": 0, "0317_card_other_idcard_count": 0, "0317_idcard_other_card_count": 0, "0317_idcard_other_device_count": 0, "0317_idcard_other_phone_count": 0, "0317_device_other_card_count": 0, "0317_device_other_idcard_count": 0, "0317_device_other_phone_count": 0, "0119_other_app_max_overdue_day": 0, "feature_123": 1, "feature_sms_cnt_less_10": 1, "feature_124": 0, "feature_cur_money_all": 0, "feature_cur_money_all_add_order": 500000, "feature_cur_money_app_add_order": 500000, "cnt_phone_60_all_clear_order": 0, "feature_1888": 0, "feature_2197": 0, "feature_2506": 0, "feature_2815": 0, "app_phone_loansprogress": 0, "app_ID_loansprogress": 0, "app_bank_loansprogress": 0, "app_gaid_loansprogress": 0, "app_phone_overdue": 0, "app_ID_overdue": 0, "app_bank_overdue": 0, "app_gaid_overdue": 0, "app_90_phone_loansprogress": 0, "app_90_ID_loansprogress": 0, "app_90_bank_loansprogress": 0, "app_90_gaid_loansprogress": 0, "app_90_phone_overdue": 0, "app_90_ID_overdue": 0, "app_90_bank_overdue": 0, "app_90_gaid_overdue": 0, "id_90_app_max_overdue_day": 0, "id_90_product_max_overdue_day": 0, "id_90_all_max_overdue_day": 0, "phone_90_app_max_overdue_day": 0, "phone_90_product_max_overdue_day": 0, "phone_90_all_max_overdue_day": 0, "bank_90_app_max_overdue_day": 0, "bank_90_product_max_overdue_day": 0, "bank_90_all_max_overdue_day": 0, "gaid_90_app_max_overdue_day": 0, "gaid_90_product_max_overdue_day": 0, "gaid_90_all_max_overdue_day": 0, "id_90_all_payout_cnt": 0, "phone_90_all_payout_cnt": 0, "bank_90_all_payout_cnt": 0, "gaid_90_all_payout_cnt": 0, "user_order_age": 0, "phone_app_1_early_repay_2_cnt": 0, "phone_app_3_early_repay_2_cnt": 0, "phone_app_5_early_repay_2_cnt": 0, "phone_app_7_early_repay_2_cnt": 0, "this_to_last_order_apply_time": -999, "has_other_app_loan": 0, "has_other_app_overdue": 0, "has_other_app_apply": 0, "all_user_order_age": -999, "other_app_last_settle_amt": 0, "first_loan_repay_money": 0, "same_as_reg_ip_30_cnt": 0, "is_reg_ip_used_by_other": 0, "main_credit_ascore_v5_and": 427, "V504": 387, "main_credit_ascore_v8_noapp": 532, "sub_fdc_loan_ascore_v4": 619, "cashloan_lst30_cnt": 2, "main_credit_ascore_v9_uneven": 442, "main_credit_ascore_v8_app": 547, "main_credit_ascore_v6_app_fdc": 504, "main_credit_ascore_v5_ios": 402, "0617_battery_status": 0, "0119_battery_is_charging": 0, "0119_battery_pct": 82, "0314_is_using_proxy_port": 0, "0314_is_using_vpn": 0, "0314_is_simulator": 1, "0314_build_name": "1.0.3", "0126_is_in_black": 0, "0126_is_in_indo_order": 1, "0201_is_in_indo_tele": 1, "0316_tele_to_apply_day": 0}, "FDC": {"history_inquiry": {"statistic": {"360_hari": 11, "30_hari": 3, ">360_hari": 17, "180_hari": 6, "3_hari": 0, "7_hari": 0, "90_hari": 6}, "last3DaysInquiry": [{"hit_by": "UANGME", "jml_data": 40, "tgl_inquiry": "2026-03-24 22:44:49"}, {"hit_by": "UANGME", "jml_data": 40, "tgl_inquiry": "2026-03-24 22:43:29"}, {"hit_by": "FINPLUS", "jml_data": 40, "tgl_inquiry": "2026-03-24 21:34:44"}, {"hit_by": "INDOSAKU", "jml_data": 40, "tgl_inquiry": "2026-03-24 23:07:00"}, {"hit_by": "PINJAMANGO", "jml_data": 40, "tgl_inquiry": "2026-03-24 23:38:45"}, {"hit_by": "CASHCEPAT", "jml_data": 40, "tgl_inquiry": "2026-03-24 22:10:19"}, {"hit_by": "ADAPUNDI", "jml_data": 40, "tgl_inquiry": "2026-03-24 21:50:38"}, {"hit_by": "IVOJI", "jml_data": 40, "tgl_inquiry": "2026-03-24 23:01:03"}]}, "pinjaman": [{"jenis_pengguna_ket": "Individual", "no_hp": "6281*****4115", "agunan": "Tidak Memiliki Agunan", "dpd_max": 2, "no_agunan": "", "tipe_pinjaman": "Multiguna", "reference": "", "pendapatan": 6000000, "tgl_jatuh_tempo_pinjaman": "2026-03-04", "dpd_terakhir": 0, "id": "2d38e8e55a60b286d71f7c85dcae049a", "id_penyelenggara": "AFDC233", "no_npwp": "", "sub_tipe_pinjaman": "Onetime Loan / Cash Loan", "email": "628****115@gmail.com", "tgl_perjanjian_borrower": "2026-02-04", "nama_borrower": "NANDI SUPRIYATNA", "sisa_pinjaman_berjalan": 0, "jenis_pengguna": 1, "no_identitas": "3272010209740940", "tgl_penyaluran_dana": "2026-02-04", "kualitas_pinjaman": "1", "status_pinjaman_ket": "Fully Paid", "penyelesaian_w_oleh": "Default", "tgl_pelaporan_data": "2026-03-04", "nilai_pendanaan": 67000, "pendanaan_syariah": false, "kualitas_pinjaman_ket": "Lancar", "status_pinjaman": "L", "nama_penjamin": ""}, {"jenis_pengguna_ket": "Individual", "no_hp": "6281*****4115", "agunan": "Tidak Memiliki Agunan", "dpd_max": 2, "no_agunan": "", "tipe_pinjaman": "Multiguna", "reference": "", "pendapatan": 6000000, "tgl_jatuh_tempo_pinjaman": "2026-05-04", "dpd_terakhir": 0, "id": "d2c3c793035289a235a29a15ff4e4693", "id_penyelenggara": "AFDC233", "no_npwp": "", "sub_tipe_pinjaman": "Onetime Loan / Cash Loan", "email": "628****115@gmail.com", "tgl_perjanjian_borrower": "2026-02-04", "nama_borrower": "NANDI SUPRIYATNA", "sisa_pinjaman_berjalan": 65140, "jenis_pengguna": 1, "no_identitas": "3272010209740940", "tgl_penyaluran_dana": "2026-02-04", "kualitas_pinjaman": "1", "status_pinjaman_ket": "Outstanding", "penyelesaian_w_oleh": "Default", "tgl_pelaporan_data": "2026-03-23", "nilai_pendanaan": 67000, "pendanaan_syariah": false, "kualitas_pinjaman_ket": "Lancar", "status_pinjaman": "O", "nama_penjamin": ""}, {"jenis_pengguna_ket": "Individual", "no_hp": "6281*****4115", "agunan": "Tidak Memiliki Agunan", "dpd_max": 2, "no_agunan": "", "tipe_pinjaman": "Multiguna", "reference": "", "pendapatan": 6000000, "tgl_jatuh_tempo_pinjaman": "2026-04-04", "dpd_terakhir": 0, "id": "c8d04a88f68316666259bfe21e950b6a", "id_penyelenggara": "AFDC233", "no_npwp": "", "sub_tipe_pinjaman": "Onetime Loan / Cash Loan", "email": "628****115@gmail.com", "tgl_perjanjian_borrower": "2026-02-04", "nama_borrower": "NANDI SUPRIYATNA", "sisa_pinjaman_berjalan": 65116, "jenis_pengguna": 1, "no_identitas": "3272010209740940", "tgl_penyaluran_dana": "2026-02-04", "kualitas_pinjaman": "1", "status_pinjaman_ket": "Outstanding", "penyelesaian_w_oleh": "Default", "tgl_pelaporan_data": "2026-03-23", "nilai_pendanaan": 67000, "pendanaan_syariah": false, "kualitas_pinjaman_ket": "Lancar", "status_pinjaman": "O", "nama_penjamin": ""}, {"jenis_pengguna_ket": "Individual", "no_hp": "6281*****4115", "agunan": "Tidak Memiliki Agunan", "dpd_max": 2, "no_agunan": "", "tipe_pinjaman": "Multiguna", "reference": "", "pendapatan": 6000000, "tgl_jatuh_tempo_pinjaman": "2026-05-22", "dpd_terakhir": 0, "id": "cd8acf7c23413e8a5fce1d1bb89efb01", "id_penyelenggara": "AFDC233", "no_npwp": "", "sub_tipe_pinjaman": "Onetime Loan / Cash Loan", "email": "628****115@gmail.com", "tgl_perjanjian_borrower": "2026-01-22", "nama_borrower": "NANDI SUPRIYATNA", "sisa_pinjaman_berjalan": 99833, "jenis_pengguna": 1, "no_identitas": "3272010209740940", "tgl_penyaluran_dana": "2026-01-22", "kualitas_pinjaman": "1", "status_pinjaman_ket": "Outstanding", "penyelesaian_w_oleh": "Default", "tgl_pelaporan_data": "2026-03-23", "nilai_pendanaan": 99833, "pendanaan_syariah": false, "kualitas_pinjaman_ket": "Lancar", "status_pinjaman": "O", "nama_penjamin": ""}, {"jenis_pengguna_ket": "Individual", "no_hp": "6281*****4115", "agunan": "Tidak Memiliki Agunan", "dpd_max": 2, "no_agunan": "", "tipe_pinjaman": "Multiguna", "reference": "", "pendapatan": 6000000, "tgl_jatuh_tempo_pinjaman": "2026-04-22", "dpd_terakhir": 0, "id": "0afcdab53e27d3a20103d55308bb85b4", "id_penyelenggara": "AFDC233", "no_npwp": "", "sub_tipe_pinjaman": "Onetime Loan / Cash Loan", "email": "628****115@gmail.com", "tgl_perjanjian_borrower": "2026-01-22", "nama_borrower": "NANDI SUPRIYATNA", "sisa_pinjaman_berjalan": 99833, "jenis_pengguna": 1, "no_identitas": "3272010209740940", "tgl_penyaluran_dana": "2026-01-22", "kualitas_pinjaman": "1", "status_pinjaman_ket": "Outstanding", "penyelesaian_w_oleh": "Default", "tgl_pelaporan_data": "2026-03-23", "nilai_pendanaan": 99833, "pendanaan_syariah": false, "kualitas_pinjaman_ket": "Lancar", "status_pinjaman": "O", "nama_penjamin": ""}, {"jenis_pengguna_ket": "Individual", "no_hp": "6281*****4115", "agunan": "Tidak Memiliki Agunan", "dpd_max": 2, "no_agunan": "", "tipe_pinjaman": "Multiguna", "reference": "", "pendapatan": 6000000, "tgl_jatuh_tempo_pinjaman": "2026-02-22", "dpd_terakhir": 0, "id": "aaccaff727803aa7123060f4c292b782", "id_penyelenggara": "AFDC233", "no_npwp": "", "sub_tipe_pinjaman": "Onetime Loan / Cash Loan", "email": "628****115@gmail.com", "tgl_perjanjian_borrower": "2026-01-22", "nama_borrower": "NANDI SUPRIYATNA", "sisa_pinjaman_berjalan": 0, "jenis_pengguna": 1, "no_identitas": "3272010209740940", "tgl_penyaluran_dana": "2026-01-22", "kualitas_pinjaman": "1", "status_pinjaman_ket": "Fully Paid", "penyelesaian_w_oleh": "Default", "tgl_pelaporan_data": "2026-02-21", "nilai_pendanaan": 99833, "pendanaan_syariah": false, "kualitas_pinjaman_ket": "Lancar", "status_pinjaman": "L", "nama_penjamin": ""}, {"jenis_pengguna_ket": "Individual", "no_hp": "6281*****4115", "agunan": "Tidak Memiliki Agunan", "dpd_max": 2, "no_agunan": "", "tipe_pinjaman": "Multiguna", "reference": "", "pendapatan": 6000000, "tgl_jatuh_tempo_pinjaman": "2026-03-22", "dpd_terakhir": 0, "id": "2fbc207f85e2e73628fe73fdddcdb547", "id_penyelenggara": "AFDC233", "no_npwp": "", "sub_tipe_pinjaman": "Onetime Loan / Cash Loan", "email": "628****115@gmail.com", "tgl_perjanjian_borrower": "2026-01-22", "nama_borrower": "NANDI SUPRIYATNA", "sisa_pinjaman_berjalan": 0, "jenis_pengguna": 1, "no_identitas": "3272010209740940", "tgl_penyaluran_dana": "2026-01-22", "kualitas_pinjaman": "1", "status_pinjaman_ket": "Fully Paid", "penyelesaian_w_oleh": "Default", "tgl_pelaporan_data": "2026-03-20", "nilai_pendanaan": 99833, "pendanaan_syariah": false, "kualitas_pinjaman_ket": "Lancar", "status_pinjaman": "L", "nama_penjamin": ""}, {"jenis_pengguna_ket": "Individual", "no_hp": "6281*****4115", "agunan": "Tidak Memiliki Agunan", "dpd_max": 2, "no_agunan": "", "tipe_pinjaman": "Multiguna", "reference": "", "pendapatan": 6000000, "tgl_jatuh_tempo_pinjaman": "2026-07-22", "dpd_terakhir": 0, "id": "daadc454e6d5c3f2bc19938929e58661", "id_penyelenggara": "AFDC233", "no_npwp": "", "sub_tipe_pinjaman": "Onetime Loan / Cash Loan", "email": "628****115@gmail.com", "tgl_perjanjian_borrower": "2026-01-22", "nama_borrower": "NANDI SUPRIYATNA", "sisa_pinjaman_berjalan": 99833, "jenis_pengguna": 1, "no_identitas": "3272010209740940", "tgl_penyaluran_dana": "2026-01-22", "kualitas_pinjaman": "1", "status_pinjaman_ket": "Outstanding", "penyelesaian_w_oleh": "Default", "tgl_pelaporan_data": "2026-03-23", "nilai_pendanaan": 99833, "pendanaan_syariah": false, "kualitas_pinjaman_ket": "Lancar", "status_pinjaman": "O", "nama_penjamin": ""}, {"jenis_pengguna_ket": "Individual", "no_hp": "6281*****4115", "agunan": "Tidak Memiliki Agunan", "dpd_max": 2, "no_agunan": "", "tipe_pinjaman": "Multiguna", "reference": "", "pendapatan": 6000000, "tgl_jatuh_tempo_pinjaman": "2026-06-22", "dpd_terakhir": 0, "id": "ac8a707f6f983572b99daaab5fb477a6", "id_penyelenggara": "AFDC233", "no_npwp": "", "sub_tipe_pinjaman": "Onetime Loan / Cash Loan", "email": "628****115@gmail.com", "tgl_perjanjian_borrower": "2026-01-22", "nama_borrower": "NANDI SUPRIYATNA", "sisa_pinjaman_berjalan": 99833, "jenis_pengguna": 1, "no_identitas": "3272010209740940", "tgl_penyaluran_dana": "2026-01-22", "kualitas_pinjaman": "1", "status_pinjaman_ket": "Outstanding", "penyelesaian_w_oleh": "Default", "tgl_pelaporan_data": "2026-03-23", "nilai_pendanaan": 99833, "pendanaan_syariah": false, "kualitas_pinjaman_ket": "Lancar", "status_pinjaman": "O", "nama_penjamin": ""}, {"jenis_pengguna_ket": "Individual", "no_hp": "6281*****4115", "agunan": "Tidak Memiliki Agunan", "dpd_max": 2, "no_agunan": "", "tipe_pinjaman": "Multiguna", "reference": "", "pendapatan": 6000000, "tgl_jatuh_tempo_pinjaman": "2025-12-06", "dpd_terakhir": 0, "id": "d3a98f82019c06ab45fec013e4ef71cb", "id_penyelenggara": "AFDC233", "no_npwp": "", "sub_tipe_pinjaman": "Onetime Loan / Cash Loan", "email": "628****115@gmail.com", "tgl_perjanjian_borrower": "2025-11-06", "nama_borrower": "NANDI SUPRIYATNA", "sisa_pinjaman_berjalan": 0, "jenis_pengguna": 1, "no_identitas": "3272010209740940", "tgl_penyaluran_dana": "2025-11-06", "kualitas_pinjaman": "1", "status_pinjaman_ket": "Fully Paid", "penyelesaian_w_oleh": "Default", "tgl_pelaporan_data": "2025-12-06", "nilai_pendanaan": 200000, "pendanaan_syariah": false, "kualitas_pinjaman_ket": "Lancar", "status_pinjaman": "L", "nama_penjamin": ""}, {"jenis_pengguna_ket": "Individual", "no_hp": "6281*****4115", "agunan": "Tidak Memiliki Agunan", "dpd_max": 2, "no_agunan": "", "tipe_pinjaman": "Multiguna", "reference": "", "pendapatan": 6000000, "tgl_jatuh_tempo_pinjaman": "2026-01-06", "dpd_terakhir": 0, "id": "d5d2cbf015d3536fab7961c17c3981bc", "id_penyelenggara": "AFDC233", "no_npwp": "", "sub_tipe_pinjaman": "Onetime Loan / Cash Loan", "email": "628****115@gmail.com", "tgl_perjanjian_borrower": "2025-11-06", "nama_borrower": "NANDI SUPRIYATNA", "sisa_pinjaman_berjalan": 0, "jenis_pengguna": 1, "no_identitas": "3272010209740940", "tgl_penyaluran_dana": "2025-11-06", "kualitas_pinjaman": "1", "status_pinjaman_ket": "Fully Paid", "penyelesaian_w_oleh": "Default", "tgl_pelaporan_data": "2026-01-05", "nilai_pendanaan": 200000, "pendanaan_syariah": false, "kualitas_pinjaman_ket": "Lancar", "status_pinjaman": "L", "nama_penjamin": ""}, {"jenis_pengguna_ket": "Individual", "no_hp": "6281*****4115", "agunan": "Tidak Memiliki Agunan", "dpd_max": 2, "no_agunan": "", "tipe_pinjaman": "Multiguna", "reference": "", "pendapatan": 6000000, "tgl_jatuh_tempo_pinjaman": "2026-02-06", "dpd_terakhir": 0, "id": "9e9541d707b14b3ad2698a8bd21bd054", "id_penyelenggara": "AFDC233", "no_npwp": "", "sub_tipe_pinjaman": "Onetime Loan / Cash Loan", "email": "628****115@gmail.com", "tgl_perjanjian_borrower": "2025-11-06", "nama_borrower": "NANDI SUPRIYATNA", "sisa_pinjaman_berjalan": 0, "jenis_pengguna": 1, "no_identitas": "3272010209740940", "tgl_penyaluran_dana": "2025-11-06", "kualitas_pinjaman": "1", "status_pinjaman_ket": "Fully Paid", "penyelesaian_w_oleh": "Default", "tgl_pelaporan_data": "2026-02-04", "nilai_pendanaan": 200000, "pendanaan_syariah": false, "kualitas_pinjaman_ket": "Lancar", "status_pinjaman": "L", "nama_penjamin": ""}, {"jenis_pengguna_ket": "Individual", "no_hp": "6281*****4115", "agunan": "Tidak Memiliki Agunan", "dpd_max": 2, "no_agunan": "", "tipe_pinjaman": "Multiguna", "reference": "", "pendapatan": 6000000, "tgl_jatuh_tempo_pinjaman": "2025-11-21", "dpd_terakhir": 0, "id": "5890150b36a94fc6a780b551de5f7964", "id_penyelenggara": "AFDC233", "no_npwp": "", "sub_tipe_pinjaman": "Onetime Loan / Cash Loan", "email": "628****115@gmail.com", "tgl_perjanjian_borrower": "2025-10-21", "nama_borrower": "NANDI SUPRIYATNA", "sisa_pinjaman_berjalan": 0, "jenis_pengguna": 1, "no_identitas": "3272010209740940", "tgl_penyaluran_dana": "2025-10-21", "kualitas_pinjaman": "1", "status_pinjaman_ket": "Fully Paid", "penyelesaian_w_oleh": "Default", "tgl_pelaporan_data": "2025-11-21", "nilai_pendanaan": 66666, "pendanaan_syariah": false, "kualitas_pinjaman_ket": "Lancar", "status_pinjaman": "L", "nama_penjamin": ""}, {"jenis_pengguna_ket": "Individual", "no_hp": "6281*****4115", "agunan": "Tidak Memiliki Agunan", "dpd_max": 2, "no_agunan": "", "tipe_pinjaman": "Multiguna", "reference": "", "pendapatan": 6000000, "tgl_jatuh_tempo_pinjaman": "2025-12-21", "dpd_terakhir": 1, "id": "af67f4fb338aae69531d19f480b762ee", "id_penyelenggara": "AFDC233", "no_npwp": "", "sub_tipe_pinjaman": "Onetime Loan / Cash Loan", "email": "628****115@gmail.com", "tgl_perjanjian_borrower": "2025-10-21", "nama_borrower": "NANDI SUPRIYATNA", "sisa_pinjaman_berjalan": 32, "jenis_pengguna": 1, "no_identitas": "3272010209740940", "tgl_penyaluran_dana": "2025-10-21", "kualitas_pinjaman": "2", "status_pinjaman_ket": "Fully Paid", "penyelesaian_w_oleh": "Default", "tgl_pelaporan_data": "2025-12-22", "nilai_pendanaan": 66666, "pendanaan_syariah": false, "kualitas_pinjaman_ket": "Dalam Perhatian Khusus", "status_pinjaman": "L", "nama_penjamin": ""}, {"jenis_pengguna_ket": "Individual", "no_hp": "6281*****4115", "agunan": "Tidak Memiliki Agunan", "dpd_max": 2, "no_agunan": "", "tipe_pinjaman": "Multiguna", "reference": "", "pendapatan": 6000000, "tgl_jatuh_tempo_pinjaman": "2026-01-21", "dpd_terakhir": 0, "id": "8ca5912e9d4e4d3876a4a82968035c66", "id_penyelenggara": "AFDC233", "no_npwp": "", "sub_tipe_pinjaman": "Onetime Loan / Cash Loan", "email": "628****115@gmail.com", "tgl_perjanjian_borrower": "2025-10-21", "nama_borrower": "NANDI SUPRIYATNA", "sisa_pinjaman_berjalan": 0, "jenis_pengguna": 1, "no_identitas": "3272010209740940", "tgl_penyaluran_dana": "2025-10-21", "kualitas_pinjaman": "1", "status_pinjaman_ket": "Fully Paid", "penyelesaian_w_oleh": "Default", "tgl_pelaporan_data": "2026-01-20", "nilai_pendanaan": 66666, "pendanaan_syariah": false, "kualitas_pinjaman_ket": "Lancar", "status_pinjaman": "L", "nama_penjamin": ""}, {"jenis_pengguna_ket": "Individual", "no_hp": "6281*****4115", "agunan": "Tidak Memiliki Agunan", "dpd_max": 2, "no_agunan": "", "tipe_pinjaman": "Multiguna", "reference": "", "pendapatan": 6000000, "tgl_jatuh_tempo_pinjaman": "2025-09-08", "dpd_terakhir": 0, "id": "878784cacfcded40b2388c30056db40c", "id_penyelenggara": "AFDC233", "no_npwp": "", "sub_tipe_pinjaman": "Onetime Loan / Cash Loan", "email": "628****115@gmail.com", "tgl_perjanjian_borrower": "2025-07-11", "nama_borrower": "NANDI SUPRIYATNA", "sisa_pinjaman_berjalan": 0, "jenis_pengguna": 1, "no_identitas": "3272010209740940", "tgl_penyaluran_dana": "2025-07-11", "kualitas_pinjaman": "1", "status_pinjaman_ket": "Fully Paid", "penyelesaian_w_oleh": "Default", "tgl_pelaporan_data": "2025-09-08", "nilai_pendanaan": 33333, "pendanaan_syariah": false, "kualitas_pinjaman_ket": "Lancar", "status_pinjaman": "L", "nama_penjamin": ""}, {"jenis_pengguna_ket": "Individual", "no_hp": "6281*****4115", "agunan": "Tidak Memiliki Agunan", "dpd_max": 2, "no_agunan": "", "tipe_pinjaman": "Multiguna", "reference": "", "pendapatan": 6000000, "tgl_jatuh_tempo_pinjaman": "2026-01-06", "dpd_terakhir": 0, "id": "0e7126045d0868249828b01cb47d6566", "id_penyelenggara": "AFDC233", "no_npwp": "", "sub_tipe_pinjaman": "Onetime Loan / Cash Loan", "email": "628****115@gmail.com", "tgl_perjanjian_borrower": "2025-07-11", "nama_borrower": "NANDI SUPRIYATNA", "sisa_pinjaman_berjalan": 0, "jenis_pengguna": 1, "no_identitas": "3272010209740940", "tgl_penyaluran_dana": "2025-07-11", "kualitas_pinjaman": "1", "status_pinjaman_ket": "Fully Paid", "penyelesaian_w_oleh": "Default", "tgl_pelaporan_data": "2025-10-05", "nilai_pendanaan": 33333, "pendanaan_syariah": false, "kualitas_pinjaman_ket": "Lancar", "status_pinjaman": "L", "nama_penjamin": ""}, {"jenis_pengguna_ket": "Individual", "no_hp": "6281*****4115", "agunan": "Tidak Memiliki Agunan", "dpd_max": 2, "no_agunan": "", "tipe_pinjaman": "Multiguna", "reference": "", "pendapatan": 6000000, "tgl_jatuh_tempo_pinjaman": "2025-11-07", "dpd_terakhir": 0, "id": "ac64245f3a0ffff3eea942b64f1b8af8", "id_penyelenggara": "AFDC233", "no_npwp": "", "sub_tipe_pinjaman": "Onetime Loan / Cash Loan", "email": "628****115@gmail.com", "tgl_perjanjian_borrower": "2025-07-11", "nama_borrower": "NANDI SUPRIYATNA", "sisa_pinjaman_berjalan": 0, "jenis_pengguna": 1, "no_identitas": "3272010209740940", "tgl_penyaluran_dana": "2025-07-11", "kualitas_pinjaman": "1", "status_pinjaman_ket": "Fully Paid", "penyelesaian_w_oleh": "Default", "tgl_pelaporan_data": "2025-10-05", "nilai_pendanaan": 33333, "pendanaan_syariah": false, "kualitas_pinjaman_ket": "Lancar", "status_pinjaman": "L", "nama_penjamin": ""}, {"jenis_pengguna_ket": "Individual", "no_hp": "6281*****4115", "agunan": "Tidak Memiliki Agunan", "dpd_max": 2, "no_agunan": "", "tipe_pinjaman": "Multiguna", "reference": "", "pendapatan": 6000000, "tgl_jatuh_tempo_pinjaman": "2025-08-09", "dpd_terakhir": 0, "id": "e3943f6c08312ec5f21c0a9d57ed95d3", "id_penyelenggara": "AFDC233", "no_npwp": "", "sub_tipe_pinjaman": "Onetime Loan / Cash Loan", "email": "628****115@gmail.com", "tgl_perjanjian_borrower": "2025-07-11", "nama_borrower": "NANDI SUPRIYATNA", "sisa_pinjaman_berjalan": 0, "jenis_pengguna": 1, "no_identitas": "3272010209740940", "tgl_penyaluran_dana": "2025-07-11", "kualitas_pinjaman": "1", "status_pinjaman_ket": "Fully Paid", "penyelesaian_w_oleh": "Default", "tgl_pelaporan_data": "2025-08-28", "nilai_pendanaan": 33333, "pendanaan_syariah": false, "kualitas_pinjaman_ket": "Lancar", "status_pinjaman": "L", "nama_penjamin": ""}, {"jenis_pengguna_ket": "Individual", "no_hp": "6281*****4115", "agunan": "Tidak Memiliki Agunan", "dpd_max": 2, "no_agunan": "", "tipe_pinjaman": "Multiguna", "reference": "", "pendapatan": 6000000, "tgl_jatuh_tempo_pinjaman": "2025-10-08", "dpd_terakhir": 0, "id": "ec762b6d535915ab6befc4187b47f9b9", "id_penyelenggara": "AFDC233", "no_npwp": "", "sub_tipe_pinjaman": "Onetime Loan / Cash Loan", "email": "628****115@gmail.com", "tgl_perjanjian_borrower": "2025-07-11", "nama_borrower": "NANDI SUPRIYATNA", "sisa_pinjaman_berjalan": 0, "jenis_pengguna": 1, "no_identitas": "3272010209740940", "tgl_penyaluran_dana": "2025-07-11", "kualitas_pinjaman": "1", "status_pinjaman_ket": "Fully Paid", "penyelesaian_w_oleh": "Default", "tgl_pelaporan_data": "2025-10-05", "nilai_pendanaan": 33333, "pendanaan_syariah": false, "kualitas_pinjaman_ket": "Lancar", "status_pinjaman": "L", "nama_penjamin": ""}, {"jenis_pengguna_ket": "Individual", "no_hp": "6281*****4115", "agunan": "Tidak Memiliki Agunan", "dpd_max": 2, "no_agunan": "", "tipe_pinjaman": "Multiguna", "reference": "", "pendapatan": 6000000, "tgl_jatuh_tempo_pinjaman": "2025-12-07", "dpd_terakhir": 0, "id": "f46401d9057c995364f0256e4c0d5cdc", "id_penyelenggara": "AFDC233", "no_npwp": "", "sub_tipe_pinjaman": "Onetime Loan / Cash Loan", "email": "628****115@gmail.com", "tgl_perjanjian_borrower": "2025-07-11", "nama_borrower": "NANDI SUPRIYATNA", "sisa_pinjaman_berjalan": 0, "jenis_pengguna": 1, "no_identitas": "3272010209740940", "tgl_penyaluran_dana": "2025-07-11", "kualitas_pinjaman": "1", "status_pinjaman_ket": "Fully Paid", "penyelesaian_w_oleh": "Default", "tgl_pelaporan_data": "2025-10-05", "nilai_pendanaan": 33333, "pendanaan_syariah": false, "kualitas_pinjaman_ket": "Lancar", "status_pinjaman": "L", "nama_penjamin": ""}, {"jenis_pengguna_ket": "Individual", "no_hp": "6281*****4115", "agunan": "Tidak Memiliki Agunan", "dpd_max": 2, "no_agunan": "", "tipe_pinjaman": "Multiguna", "reference": "", "pendapatan": 6000000, "tgl_jatuh_tempo_pinjaman": "2025-07-10", "dpd_terakhir": 0, "id": "870d121d62e25e71995cf6557e1ffaad", "id_penyelenggara": "AFDC233", "no_npwp": "", "sub_tipe_pinjaman": "Onetime Loan / Cash Loan", "email": "628****115@gmail.com", "tgl_perjanjian_borrower": "2025-05-12", "nama_borrower": "NANDI SUPRIYATNA", "sisa_pinjaman_berjalan": 0, "jenis_pengguna": 1, "no_identitas": "3272010209740940", "tgl_penyaluran_dana": "2025-05-12", "kualitas_pinjaman": "1", "status_pinjaman_ket": "Fully Paid", "penyelesaian_w_oleh": "Default", "tgl_pelaporan_data": "2025-07-10", "nilai_pendanaan": 100000, "pendanaan_syariah": false, "kualitas_pinjaman_ket": "Lancar", "status_pinjaman": "L", "nama_penjamin": ""}, {"jenis_pengguna_ket": "Individual", "no_hp": "6281*****4115", "agunan": "Tidak Memiliki Agunan", "dpd_max": 2, "no_agunan": "", "tipe_pinjaman": "Multiguna", "reference": "", "pendapatan": 6000000, "tgl_jatuh_tempo_pinjaman": "2025-08-09", "dpd_terakhir": 0, "id": "8719db9b078bbbc579900e4093fe1380", "id_penyelenggara": "AFDC233", "no_npwp": "", "sub_tipe_pinjaman": "Onetime Loan / Cash Loan", "email": "628****115@gmail.com", "tgl_perjanjian_borrower": "2025-05-12", "nama_borrower": "NANDI SUPRIYATNA", "sisa_pinjaman_berjalan": 0, "jenis_pengguna": 1, "no_identitas": "3272010209740940", "tgl_penyaluran_dana": "2025-05-12", "kualitas_pinjaman": "1", "status_pinjaman_ket": "Fully Paid", "penyelesaian_w_oleh": "Default", "tgl_pelaporan_data": "2025-07-11", "nilai_pendanaan": 100000, "pendanaan_syariah": false, "kualitas_pinjaman_ket": "Lancar", "status_pinjaman": "L", "nama_penjamin": ""}, {"jenis_pengguna_ket": "Individual", "no_hp": "6281*****4115", "agunan": "Tidak Memiliki Agunan", "dpd_max": 2, "no_agunan": "", "tipe_pinjaman": "Multiguna", "reference": "", "pendapatan": 6000000, "tgl_jatuh_tempo_pinjaman": "2025-06-10", "dpd_terakhir": 1, "id": "68763540819fc3ea1b6497c2db1ae095", "id_penyelenggara": "AFDC233", "no_npwp": "", "sub_tipe_pinjaman": "Onetime Loan / Cash Loan", "email": "628****115@gmail.com", "tgl_perjanjian_borrower": "2025-05-12", "nama_borrower": "NANDI SUPRIYATNA", "sisa_pinjaman_berjalan": 48, "jenis_pengguna": 1, "no_identitas": "3272010209740940", "tgl_penyaluran_dana": "2025-05-12", "kualitas_pinjaman": "2", "status_pinjaman_ket": "Fully Paid", "penyelesaian_w_oleh": "Default", "tgl_pelaporan_data": "2025-06-11", "nilai_pendanaan": 100000, "pendanaan_syariah": false, "kualitas_pinjaman_ket": "Dalam Perhatian Khusus", "status_pinjaman": "L", "nama_penjamin": ""}, {"jenis_pengguna_ket": "Individual", "no_hp": "6281*****4115", "agunan": "Tidak Memiliki Agunan", "dpd_max": 2, "no_agunan": "", "tipe_pinjaman": "Multiguna", "reference": "", "pendapatan": 6000000, "tgl_jatuh_tempo_pinjaman": "2024-11-10", "dpd_terakhir": 0, "id": "037b66a815c7ce3bd2daa2edd7dc6e1e", "id_penyelenggara": "AFDC233", "no_npwp": "", "sub_tipe_pinjaman": "Onetime Loan / Cash Loan", "email": "628****115@gmail.com", "tgl_perjanjian_borrower": "2024-08-13", "nama_borrower": "NANDI SUPRIYATNA", "sisa_pinjaman_berjalan": 0, "jenis_pengguna": 1, "no_identitas": "3272010209740940", "tgl_penyaluran_dana": "2024-08-13", "kualitas_pinjaman": "1", "status_pinjaman_ket": "Fully Paid", "penyelesaian_w_oleh": "Default", "tgl_pelaporan_data": "2024-10-04", "nilai_pendanaan": 66666, "pendanaan_syariah": false, "kualitas_pinjaman_ket": "Lancar", "status_pinjaman": "L", "nama_penjamin": ""}, {"jenis_pengguna_ket": "Individual", "no_hp": "6281*****4115", "agunan": "Tidak Memiliki Agunan", "dpd_max": 2, "no_agunan": "", "tipe_pinjaman": "Multiguna", "reference": "", "pendapatan": 6000000, "tgl_jatuh_tempo_pinjaman": "2024-09-11", "dpd_terakhir": 0, "id": "dc947a38a483b7cee52a1a4396546ff6", "id_penyelenggara": "AFDC233", "no_npwp": "", "sub_tipe_pinjaman": "Onetime Loan / Cash Loan", "email": "628****115@gmail.com", "tgl_perjanjian_borrower": "2024-08-13", "nama_borrower": "NANDI SUPRIYATNA", "sisa_pinjaman_berjalan": 0, "jenis_pengguna": 1, "no_identitas": "3272010209740940", "tgl_penyaluran_dana": "2024-08-13", "kualitas_pinjaman": "1", "status_pinjaman_ket": "Fully Paid", "penyelesaian_w_oleh": "Default", "tgl_pelaporan_data": "2024-09-10", "nilai_pendanaan": 66666, "pendanaan_syariah": false, "kualitas_pinjaman_ket": "Lancar", "status_pinjaman": "L", "nama_penjamin": ""}, {"jenis_pengguna_ket": "Individual", "no_hp": "6281*****4115", "agunan": "Tidak Memiliki Agunan", "dpd_max": 2, "no_agunan": "", "tipe_pinjaman": "Multiguna", "reference": "", "pendapatan": 6000000, "tgl_jatuh_tempo_pinjaman": "2024-10-11", "dpd_terakhir": 0, "id": "632162c48b6d73b7b9f628dfe14b9003", "id_penyelenggara": "AFDC233", "no_npwp": "", "sub_tipe_pinjaman": "Onetime Loan / Cash Loan", "email": "628****115@gmail.com", "tgl_perjanjian_borrower": "2024-08-13", "nama_borrower": "NANDI SUPRIYATNA", "sisa_pinjaman_berjalan": 0, "jenis_pengguna": 1, "no_identitas": "3272010209740940", "tgl_penyaluran_dana": "2024-08-13", "kualitas_pinjaman": "1", "status_pinjaman_ket": "Fully Paid", "penyelesaian_w_oleh": "Default", "tgl_pelaporan_data": "2024-10-04", "nilai_pendanaan": 66666, "pendanaan_syariah": false, "kualitas_pinjaman_ket": "Lancar", "status_pinjaman": "L", "nama_penjamin": ""}, {"jenis_pengguna_ket": "Individual", "no_hp": "6281*****4115", "agunan": "Tidak Memiliki Agunan", "dpd_max": 2, "no_agunan": "", "tipe_pinjaman": "Multiguna", "reference": "", "pendapatan": 0, "tgl_jatuh_tempo_pinjaman": "2024-07-06", "dpd_terakhir": 2, "id": "fe95653389cd3c30df50f97c1547e06a", "id_penyelenggara": "AFDC233", "sub_tipe_pinjaman": "Onetime Loan / Cash Loan", "email": "628****115@gmail.com", "tgl_perjanjian_borrower": "2024-06-07", "nama_borrower": "NANDI SUPRIYATNA", "sisa_pinjaman_berjalan": 132, "jenis_pengguna": 1, "no_identitas": "3272010209740940", "tgl_penyaluran_dana": "2024-06-07", "kualitas_pinjaman": "2", "status_pinjaman_ket": "Fully Paid", "penyelesaian_w_oleh": "Default", "tgl_pelaporan_data": "2024-07-08", "nilai_pendanaan": 66666, "pendanaan_syariah": false, "kualitas_pinjaman_ket": "Dalam Perhatian Khusus", "status_pinjaman": "L", "nama_penjamin": ""}, {"jenis_pengguna_ket": "Individual", "no_hp": "6281*****4115", "agunan": "Tidak Memiliki Agunan", "dpd_max": 2, "no_agunan": "", "tipe_pinjaman": "Multiguna", "reference": "", "pendapatan": 6000000, "tgl_jatuh_tempo_pinjaman": "2024-09-04", "dpd_terakhir": 0, "id": "81fd30f9cdb0799bf239add0b65063e4", "id_penyelenggara": "AFDC233", "no_npwp": "", "sub_tipe_pinjaman": "Onetime Loan / Cash Loan", "email": "628****115@gmail.com", "tgl_perjanjian_borrower": "2024-06-07", "nama_borrower": "NANDI SUPRIYATNA", "sisa_pinjaman_berjalan": 0, "jenis_pengguna": 1, "no_identitas": "3272010209740940", "tgl_penyaluran_dana": "2024-06-07", "kualitas_pinjaman": "1", "status_pinjaman_ket": "Fully Paid", "penyelesaian_w_oleh": "Default", "tgl_pelaporan_data": "2024-08-08", "nilai_pendanaan": 66666, "pendanaan_syariah": false, "kualitas_pinjaman_ket": "Lancar", "status_pinjaman": "L", "nama_penjamin": ""}, {"jenis_pengguna_ket": "Individual", "no_hp": "6281*****4115", "agunan": "Tidak Memiliki Agunan", "dpd_max": 2, "no_agunan": "", "tipe_pinjaman": "Multiguna", "reference": "", "pendapatan": 6000000, "tgl_jatuh_tempo_pinjaman": "2024-08-05", "dpd_terakhir": 0, "id": "3b4ee52e7186a42f38d40bf8642c7609", "id_penyelenggara": "AFDC233", "no_npwp": "", "sub_tipe_pinjaman": "Onetime Loan / Cash Loan", "email": "628****115@gmail.com", "tgl_perjanjian_borrower": "2024-06-07", "nama_borrower": "NANDI SUPRIYATNA", "sisa_pinjaman_berjalan": 0, "jenis_pengguna": 1, "no_identitas": "3272010209740940", "tgl_penyaluran_dana": "2024-06-07", "kualitas_pinjaman": "1", "status_pinjaman_ket": "Fully Paid", "penyelesaian_w_oleh": "Default", "tgl_pelaporan_data": "2024-08-05", "nilai_pendanaan": 66666, "pendanaan_syariah": false, "kualitas_pinjaman_ket": "Lancar", "status_pinjaman": "L", "nama_penjamin": ""}, {"jenis_pengguna_ket": "Individual", "no_hp": "6281*****4115", "agunan": "Tidak Memiliki Agunan", "dpd_max": 0, "no_agunan": "", "tipe_pinjaman": "Multiguna", "reference": "", "pendapatan": 0, "tgl_jatuh_tempo_pinjaman": "2024-02-02", "dpd_terakhir": 0, "id": "b1396ce95980f98eebf1b46e1ee5c8f8", "id_penyelenggara": "AFDC243", "no_npwp": "", "sub_tipe_pinjaman": "Onetime Loan / Cash Loan", "email": "azn****d97@gmail.com", "tgl_perjanjian_borrower": "2024-01-03", "nama_borrower": "NANDI SUPRIYATNA", "sisa_pinjaman_berjalan": 0, "jenis_pengguna": 1, "no_identitas": "3272010209740940", "tgl_penyaluran_dana": "2024-01-03", "kualitas_pinjaman": "1", "status_pinjaman_ket": "Fully Paid", "penyelesaian_w_oleh": "Default", "tgl_pelaporan_data": "2025-01-12", "nilai_pendanaan": 900000, "pendanaan_syariah": false, "kualitas_pinjaman_ket": "Lancar", "status_pinjaman": "L", "nama_penjamin": ""}, {"jenis_pengguna_ket": "Individual", "no_hp": "6281*****4115", "agunan": "Tidak Memiliki Agunan", "dpd_max": 0, "no_agunan": "", "tipe_pinjaman": "Multiguna", "reference": "", "pendapatan": 0, "tgl_jatuh_tempo_pinjaman": "2024-01-08", "dpd_terakhir": 0, "id": "a36707cef9db0d3694f2f8b8cde4a275", "id_penyelenggara": "AFDC243", "no_npwp": "", "sub_tipe_pinjaman": "Onetime Loan / Cash Loan", "email": "azn****d97@gmail.com", "tgl_perjanjian_borrower": "2023-12-09", "nama_borrower": "NANDI SUPRIYATNA", "sisa_pinjaman_berjalan": 0, "jenis_pengguna": 1, "no_identitas": "3272010209740940", "tgl_penyaluran_dana": "2023-12-09", "kualitas_pinjaman": "1", "status_pinjaman_ket": "Fully Paid", "penyelesaian_w_oleh": "Default", "tgl_pelaporan_data": "2025-01-12", "nilai_pendanaan": 600000, "pendanaan_syariah": false, "kualitas_pinjaman_ket": "Lancar", "status_pinjaman": "L", "nama_penjamin": ""}, {"jenis_pengguna_ket": "Individual", "no_hp": "6281*****4115", "agunan": "Tidak Memiliki Agunan", "dpd_max": 0, "no_agunan": "", "tipe_pinjaman": "Multiguna", "reference": "", "pendapatan": 0, "tgl_jatuh_tempo_pinjaman": "2024-01-03", "dpd_terakhir": 0, "id": "519057ff6b35f61a0529541346758079", "id_penyelenggara": "AFDC243", "no_npwp": "", "sub_tipe_pinjaman": "Onetime Loan / Cash Loan", "email": "azn****d97@gmail.com", "tgl_perjanjian_borrower": "2023-12-04", "nama_borrower": "NANDI SUPRIYATNA", "sisa_pinjaman_berjalan": 0, "jenis_pengguna": 1, "no_identitas": "3272010209740940", "tgl_penyaluran_dana": "2023-12-04", "kualitas_pinjaman": "1", "status_pinjaman_ket": "Fully Paid", "penyelesaian_w_oleh": "Default", "tgl_pelaporan_data": "2025-01-12", "nilai_pendanaan": 1500000, "pendanaan_syariah": false, "kualitas_pinjaman_ket": "Lancar", "status_pinjaman": "L", "nama_penjamin": ""}, {"jenis_pengguna_ket": "Individual", "no_hp": "6281*****4115", "agunan": "Tidak Memiliki Agunan", "dpd_max": 0, "no_agunan": "", "tipe_pinjaman": "Multiguna", "reference": "", "pendapatan": 0, "tgl_jatuh_tempo_pinjaman": "2023-12-05", "dpd_terakhir": 0, "id": "2c59aa2adecc7bb8b6a4cbf8d199b554", "id_penyelenggara": "AFDC243", "no_npwp": "", "sub_tipe_pinjaman": "Onetime Loan / Cash Loan", "email": "azn****d97@gmail.com", "tgl_perjanjian_borrower": "2023-11-05", "nama_borrower": "NANDI SUPRIYATNA", "sisa_pinjaman_berjalan": 0, "jenis_pengguna": 1, "no_identitas": "3272010209740940", "tgl_penyaluran_dana": "2023-11-05", "kualitas_pinjaman": "1", "status_pinjaman_ket": "Fully Paid", "penyelesaian_w_oleh": "Default", "tgl_pelaporan_data": "2025-01-12", "nilai_pendanaan": 500000, "pendanaan_syariah": false, "kualitas_pinjaman_ket": "Lancar", "status_pinjaman": "L", "nama_penjamin": ""}, {"jenis_pengguna_ket": "Individual", "no_hp": "6281*****4115", "agunan": "Tidak Memiliki Agunan", "dpd_max": 0, "no_agunan": "", "tipe_pinjaman": "Multiguna", "reference": "", "pendapatan": 0, "tgl_jatuh_tempo_pinjaman": "2023-11-03", "dpd_terakhir": 0, "id": "9756ab42e5b0378d8db2e9f6241cd81c", "id_penyelenggara": "AFDC243", "no_npwp": "", "sub_tipe_pinjaman": "Onetime Loan / Cash Loan", "email": "azn****d97@gmail.com", "tgl_perjanjian_borrower": "2023-10-04", "nama_borrower": "NANDI SUPRIYATNA", "sisa_pinjaman_berjalan": 0, "jenis_pengguna": 1, "no_identitas": "3272010209740940", "tgl_penyaluran_dana": "2023-10-04", "kualitas_pinjaman": "1", "status_pinjaman_ket": "Fully Paid", "penyelesaian_w_oleh": "Default", "tgl_pelaporan_data": "2025-01-12", "nilai_pendanaan": 600000, "pendanaan_syariah": false, "kualitas_pinjaman_ket": "Lancar", "status_pinjaman": "L", "nama_penjamin": ""}, {"jenis_pengguna_ket": "Individual", "no_hp": "6281*****4115", "agunan": "Tidak Memiliki Agunan", "dpd_max": 0, "no_agunan": "", "tipe_pinjaman": "Multiguna", "reference": "", "pendapatan": 0, "tgl_jatuh_tempo_pinjaman": "2023-10-07", "dpd_terakhir": 0, "id": "5040b9b7d43adf329116ffa5ab94bdbf", "id_penyelenggara": "AFDC243", "no_npwp": "", "sub_tipe_pinjaman": "Onetime Loan / Cash Loan", "email": "azn****d97@gmail.com", "tgl_perjanjian_borrower": "2023-09-07", "nama_borrower": "NANDI SUPRIYATNA", "sisa_pinjaman_berjalan": 0, "jenis_pengguna": 1, "no_identitas": "3272010209740940", "tgl_penyaluran_dana": "2023-09-07", "kualitas_pinjaman": "1", "status_pinjaman_ket": "Fully Paid", "penyelesaian_w_oleh": "Default", "tgl_pelaporan_data": "2025-01-12", "nilai_pendanaan": 300000, "pendanaan_syariah": false, "kualitas_pinjaman_ket": "Lancar", "status_pinjaman": "L", "nama_penjamin": ""}, {"jenis_pengguna_ket": "Individual", "no_hp": "6281*****4115", "agunan": "Tidak Memiliki Agunan", "dpd_max": 0, "no_agunan": "", "tipe_pinjaman": "Multiguna", "reference": "", "pendapatan": 0, "tgl_jatuh_tempo_pinjaman": "2023-09-09", "dpd_terakhir": 0, "id": "0bf6d71a1ebc3f82576421f28fff8980", "id_penyelenggara": "AFDC243", "no_npwp": "", "sub_tipe_pinjaman": "Onetime Loan / Cash Loan", "email": "azn****d97@gmail.com", "tgl_perjanjian_borrower": "2023-08-10", "nama_borrower": "NANDI SUPRIYATNA", "sisa_pinjaman_berjalan": 0, "jenis_pengguna": 1, "no_identitas": "3272010209740940", "tgl_penyaluran_dana": "2023-08-10", "kualitas_pinjaman": "1", "status_pinjaman_ket": "Fully Paid", "penyelesaian_w_oleh": "Default", "tgl_pelaporan_data": "2025-01-12", "nilai_pendanaan": 200000, "pendanaan_syariah": false, "kualitas_pinjaman_ket": "Lancar", "status_pinjaman": "L", "nama_penjamin": ""}, {"jenis_pengguna_ket": "Individual", "no_hp": "6281*****7877", "agunan": "Tidak Memiliki Agunan", "dpd_max": 2261, "no_agunan": "", "tipe_pinjaman": "Multiguna", "reference": "", "pendapatan": 7000000, "tgl_jatuh_tempo_pinjaman": "2019-05-12", "dpd_terakhir": 2261, "id": "0f236fc05304bebf53739a5ea86e3bc2", "id_penyelenggara": "AFDC245", "no_npwp": "", "sub_tipe_pinjaman": "Onetime Loan / Cash Loan", "email": "m_n****640@gmail.com", "tgl_perjanjian_borrower": "2019-04-15", "nama_borrower": "NANDI SUPRIYATNA", "sisa_pinjaman_berjalan": 800000, "jenis_pengguna": 1, "no_identitas": "3272010209740940", "tgl_penyaluran_dana": "2019-04-15", "kualitas_pinjaman": "5", "status_pinjaman_ket": "Write-Off", "penyelesaian_w_oleh": "Insurance", "tgl_pelaporan_data": "2025-07-30", "nilai_pendanaan": 800000, "pendanaan_syariah": false, "kualitas_pinjaman_ket": "Macet", "status_pinjaman": "W", "nama_penjamin": ""}, {"jenis_pengguna_ket": "Individual", "agunan": "Tidak Memiliki Agunan", "dpd_max": 383, "no_agunan": "", "tipe_pinjaman": "Multiguna", "pendapatan": 0, "tgl_jatuh_tempo_pinjaman": "2019-05-12", "dpd_terakhir": 383, "id": "3b5261acf19c2695fddd5e9f5298a5ee", "id_penyelenggara": "AFDC232", "sub_tipe_pinjaman": "Default", "tgl_perjanjian_borrower": "2019-04-13", "nama_borrower": "NANDI SUPRIYATNA", "sisa_pinjaman_berjalan": 300000, "jenis_pengguna": 1, "no_identitas": "3272010209740940", "tgl_penyaluran_dana": "2019-04-13", "kualitas_pinjaman": "5", "status_pinjaman_ket": "Write-Off", "penyelesaian_w_oleh": "Default", "tgl_pelaporan_data": "2020-05-29", "nilai_pendanaan": 300000, "pendanaan_syariah": false, "kualitas_pinjaman_ket": "Macet", "status_pinjaman": "W", "nama_penjamin": ""}, {"jenis_pengguna_ket": "Individual", "no_hp": "6281*****7877", "agunan": "Tidak Memiliki Agunan", "dpd_max": 1718, "no_agunan": "", "tipe_pinjaman": "Multiguna", "reference": "", "pendapatan": 0, "tgl_jatuh_tempo_pinjaman": "2019-05-03", "dpd_terakhir": 1718, "id": "b28ea99bc61bffa379c7f5fa5bd2c4bd", "id_penyelenggara": "AFDC230", "no_npwp": "250195781405000", "sub_tipe_pinjaman": "Onetime Loan / Cash Loan", "email": "ile****i74@gmail.com", "tgl_perjanjian_borrower": "2019-04-12", "nama_borrower": "NANDI SUPRIYATNA", "sisa_pinjaman_berjalan": 600000, "jenis_pengguna": 1, "no_identitas": "3272010209740940", "tgl_penyaluran_dana": "2019-04-12", "kualitas_pinjaman": "5", "status_pinjaman_ket": "Write-Off", "penyelesaian_w_oleh": "Insurance", "tgl_pelaporan_data": "2024-01-15", "nilai_pendanaan": 600000, "pendanaan_syariah": false, "kualitas_pinjaman_ket": "Macet", "status_pinjaman": "W", "nama_penjamin": ""}], "platform_aktif": {"jumlahPlatformAktif": 1, "platform": ["AFDC233"]}}, "Indo_XD_score": -999}}