{"country": "INDO", "eventType": "Indo_new_0115", "orderId": "id002mkxf202602231115180431654", "applyTime": 1771820641000, "params": {"base": {"appname": "flex-rupiah", "newCustomer": 1, "birthday": "01-07-2004", "job": "", "channel": "未知渠道", "applyTime": 1771820641000, "gender": 1, "phone": "+6282342327450", "gaid": "b0ab7b34-aa9a-42d5-8835-5950cdf76fcf", "bankCard": "063001061419504", "idCard": "5206020107041139", "marita": 1, "children": 0, "salary": 0, "workYears": 3, "state": 0, "relationship1": 2, "relationship2": 2, "use": 0, "uaClientType": "Android", "orderSource": "self", "userTg": "XJX_0", "packageName": "com.flex.rupiah.trusta.flexrupiah"}, "appList": [{"inTime": 1748016626812, "upTime": 1751123606646, "appName": "Semua pengunduh video", "appType": 0, "versionName": "2.0.78", "packageX": "allinone.videodownloader.savevideos", "versionCode": "2.0.78"}, {"inTime": 1771035688195, "upTime": 1771035688195, "appName": "JMO", "appType": 0, "versionName": "4.15.17", "packageX": "com.bpjstku", "versionCode": "4.15.17"}, {"inTime": 1736190262000, "upTime": 1736190262000, "appName": "Layar Kunci Sekali Ketuk", "appType": 0, "versionName": "8.0.7", "packageX": "com.coloros.onekeylockscreen", "versionCode": "8.0.7"}, {"inTime": 1736190262000, "upTime": 1736190262000, "appName": "Perangkat Nirkabel OPPO", "appType": 0, "versionName": "3.6.82", "packageX": "com.coloros.oppopods", "versionCode": "3.6.82"}, {"inTime": 1751194534563, "upTime": 1771789756534, "appName": "Lite", "appType": 0, "versionName": "500.0.0.6.103", "packageX": "com.facebook.lite", "versionCode": "500.0.0.6.103"}, {"inTime": 1770404452000, "upTime": 1770404452000, "appName": "Fineasy", "appType": 0, "versionName": "2.4.12", "packageX": "com.fintech.life", "versionCode": "2.4.12"}, {"inTime": 1771820019283, "upTime": 1771820019283, "appName": "Asisten Pinjaman", "appType": 0, "versionName": "1.0.2", "packageX": "com.flex.rupiah.trusta.flexrupiah", "versionCode": "1.0.2"}, {"inTime": 1746852169000, "upTime": 1771246912028, "appName": "Drive", "appType": 0, "versionName": "2.26.067.0.all.alldpi", "packageX": "com.google.android.apps.docs", "versionCode": "2.26.067.0.all.alldpi"}, {"inTime": 1746967221000, "upTime": 1746967221000, "appName": "Google Podcasts", "appType": 0, "versionName": "1.0.0.266384425", "packageX": "com.google.android.apps.podcasts", "versionCode": "1.0.0.266384425"}, {"inTime": 1746967222000, "upTime": 1746967222000, "appName": "Google One", "appType": 0, "versionName": "1.54.285215801", "packageX": "com.google.android.apps.subscriptions.red", "versionCode": "1.54.285215801"}, {"inTime": 1746967215000, "upTime": 1771246977761, "appName": "YouTube Music", "appType": 0, "versionName": "9.06.51", "packageX": "com.google.android.apps.youtube.music", "versionCode": "9.06.51"}, {"inTime": 1747105925670, "upTime": 1769971244264, "appName": "Android System Key Verifier", "appType": 0, "versionName": "1.307.858531162", "packageX": "com.google.android.contactkeys", "versionCode": "1.307.858531162"}, {"inTime": 1764918997728, "upTime": 1769971221637, "appName": "Android System SafetyCore", "appType": 0, "versionName": "1.0.858530856", "packageX": "com.google.android.safetycore", "versionCode": "1.0.858530856"}, {"inTime": 1744946271000, "upTime": 1771246865165, "appName": "Google TV", "appType": 0, "versionName": "4.39.4162.864772944.4-release", "packageX": "com.google.android.videos", "versionCode": "4.39.4162.864772944.4-release"}, {"inTime": 1759442651797, "upTime": 1771246108154, "appName": "GreatDay 8", "appType": 0, "versionName": "1.77.0", "packageX": "com.greatday.app", "versionCode": "1.77.0"}, {"inTime": 1750970217775, "upTime": 1771247130140, "appName": "Muslim", "appType": 0, "versionName": "6.1.1", "packageX": "com.hundred.qibla", "versionCode": "6.1.1"}, {"inTime": 1771231836988, "upTime": 1771231836988, "appName": "MiChat", "appType": 0, "versionName": "1.4.697", "packageX": "com.michatapp.im", "versionCode": "1.4.697"}, {"inTime": 1748261783930, "upTime": 1750365846494, "appName": "Nanovest", "appType": 0, "versionName": "4.11.0", "packageX": "com.nanovest.prod", "versionCode": "4.11.0"}, {"inTime": 1759445320625, "upTime": 1771246261900, "appName": "Timemark", "appType": 0, "versionName": "v10.0.36", "packageX": "com.oceangalaxy.camera.new", "versionCode": "v10.0.36"}, {"inTime": 1763538693637, "upTime": 1763538693637, "appName": "Penjaga SMS", "appType": 0, "versionName": "1.0.1", "packageX": "com.oplus.providers.telephony.permissions.patch", "versionCode": "1.0.1"}, {"inTime": 1757902605627, "upTime": 1771246605822, "appName": "Privy", "appType": 0, "versionName": "5.17.3", "packageX": "com.privygate.privyid", "versionCode": "5.17.3"}, {"inTime": 1770629493945, "upTime": 1770706694953, "appName": "TikTok", "appType": 0, "versionName": "43.8.3", "packageX": "com.ss.android.ugc.trill", "versionCode": "43.8.3"}, {"inTime": 1755621346895, "upTime": 1771231566545, "appName": "WhatsApp", "appType": 0, "versionName": "2.26.5.74", "packageX": "com.whatsapp", "versionCode": "2.26.5.74"}, {"inTime": 1760308468396, "upTime": 1766501547785, "appName": "Livin' by Mandiri", "appType": 0, "versionName": "3.2.0", "packageX": "id.bmri.livin", "versionCode": "3.2.0"}, {"inTime": 1768694690492, "upTime": 1771246414244, "appName": "SeaBank", "appType": 0, "versionName": "3.38.0", "packageX": "id.co.bankbkemobile.digitalbank", "versionCode": "3.38.0"}, {"inTime": 1759332343528, "upTime": 1770097820621, "appName": "BRImo", "appType": 0, "versionName": "2.93.0", "packageX": "id.co.bri.brimo", "versionCode": "2.93.0"}], "smsList": [], "FDC": {"history_inquiry": {"statistic": {"360_hari": 25, "30_hari": 13, ">360_hari": 33, "180_hari": 25, "3_hari": 2, "7_hari": 4, "90_hari": 17}, "last3DaysInquiry": [{"hit_by": "TRUSTIQ", "jml_data": 9, "tgl_inquiry": "2026-02-22 09:47:45"}, {"hit_by": "TRUSTIQ", "jml_data": 9, "tgl_inquiry": "2026-02-22 09:44:21"}, {"hit_by": "LUMBUNG DANA", "jml_data": 9, "tgl_inquiry": "2026-02-23 07:33:30"}, {"hit_by": "BANTUSAKU", "jml_data": 9, "tgl_inquiry": "2026-02-22 09:13:11"}]}, "pinjaman": [{"jenis_pengguna_ket": "Individual", "no_hp": "6282*****7450", "agunan": "Tidak Memiliki Agunan", "dpd_max": 0, "no_agunan": "", "tipe_pinjaman": "Multiguna", "reference": "", "pendapatan": 8000000, "tgl_jatuh_tempo_pinjaman": "2026-07-11", "dpd_terakhir": 0, "id": "b0bd2704e2b473244a028ac85ac43dfc", "id_penyelenggara": "AFDC148", "no_npwp": "", "sub_tipe_pinjaman": "Paylater/ Line Of Credit", "email": "awa****994@gmail.com", "tgl_perjanjian_borrower": "2026-02-11", "nama_borrower": "AWALUDDIN", "sisa_pinjaman_berjalan": 612000, "jenis_pengguna": 1, "no_identitas": "5206020107041139", "tgl_penyaluran_dana": "2026-02-11", "kualitas_pinjaman": "1", "status_pinjaman_ket": "Outstanding", "penyelesaian_w_oleh": "Default", "tgl_pelaporan_data": "2026-02-20", "nilai_pendanaan": 612000, "pendanaan_syariah": false, "kualitas_pinjaman_ket": "Lancar", "status_pinjaman": "O", "nama_penjamin": ""}, {"jenis_pengguna_ket": "Individual", "no_hp": "6282*****7450", "agunan": "Tidak Memiliki Agunan", "dpd_max": 0, "no_agunan": "", "tipe_pinjaman": "Multiguna", "reference": "", "pendapatan": 0, "tgl_jatuh_tempo_pinjaman": "2026-04-01", "dpd_terakhir": 0, "id": "12a073a34fa2924961e6873f3a688a60", "id_penyelenggara": "AFDC255", "no_npwp": "", "sub_tipe_pinjaman": "Onetime Loan / Cash Loan", "email": "awa****994@gmail.com", "tgl_perjanjian_borrower": "2026-01-01", "nama_borrower": "AWALUDDIN", "sisa_pinjaman_berjalan": 0, "jenis_pengguna": 1, "no_identitas": "5206020107041139", "tgl_penyaluran_dana": "2026-01-01", "kualitas_pinjaman": "1", "status_pinjaman_ket": "Fully Paid", "penyelesaian_w_oleh": "Default", "tgl_pelaporan_data": "2026-01-01", "nilai_pendanaan": 312000, "pendanaan_syariah": false, "kualitas_pinjaman_ket": "Lancar", "status_pinjaman": "L", "nama_penjamin": ""}, {"jenis_pengguna_ket": "Individual", "no_hp": "6282*****7450", "agunan": "Tidak Memiliki Agunan", "dpd_max": 0, "no_agunan": "", "tipe_pinjaman": "Multiguna", "reference": "", "pendapatan": 0, "tgl_jatuh_tempo_pinjaman": "2026-03-02", "dpd_terakhir": 0, "id": "861616550b8a02ab57851af624025802", "id_penyelenggara": "AFDC255", "no_npwp": "", "sub_tipe_pinjaman": "Onetime Loan / Cash Loan", "email": "awa****994@gmail.com", "tgl_perjanjian_borrower": "2025-12-02", "nama_borrower": "AWALUDDIN", "sisa_pinjaman_berjalan": 0, "jenis_pengguna": 1, "no_identitas": "5206020107041139", "tgl_penyaluran_dana": "2025-12-02", "kualitas_pinjaman": "1", "status_pinjaman_ket": "Fully Paid", "penyelesaian_w_oleh": "Default", "tgl_pelaporan_data": "2026-01-01", "nilai_pendanaan": 194000, "pendanaan_syariah": false, "kualitas_pinjaman_ket": "Lancar", "status_pinjaman": "L", "nama_penjamin": ""}, {"jenis_pengguna_ket": "Individual", "no_hp": "6282*****7450", "agunan": "Tidak Memiliki Agunan", "dpd_max": 0, "no_agunan": "", "tipe_pinjaman": "Multiguna", "reference": "", "pendapatan": 0, "tgl_jatuh_tempo_pinjaman": "2025-12-05", "dpd_terakhir": 0, "id": "8d313b708cd77c6448cc046d36af609a", "id_penyelenggara": "AFDC255", "no_npwp": "", "sub_tipe_pinjaman": "Onetime Loan / Cash Loan", "email": "awa****994@gmail.com", "tgl_perjanjian_borrower": "2025-11-05", "nama_borrower": "AWALUDDIN", "sisa_pinjaman_berjalan": 0, "jenis_pengguna": 1, "no_identitas": "5206020107041139", "tgl_penyaluran_dana": "2025-11-05", "kualitas_pinjaman": "1", "status_pinjaman_ket": "Fully Paid", "penyelesaian_w_oleh": "Default", "tgl_pelaporan_data": "2025-12-01", "nilai_pendanaan": 119000, "pendanaan_syariah": false, "kualitas_pinjaman_ket": "Lancar", "status_pinjaman": "L", "nama_penjamin": ""}, {"jenis_pengguna_ket": "Individual", "no_hp": "6281*****5063", "agunan": "Tidak Memiliki Agunan", "dpd_max": 0, "no_agunan": "", "tipe_pinjaman": "Multiguna", "reference": "", "pendapatan": 0, "tgl_jatuh_tempo_pinjaman": "2021-11-21", "dpd_terakhir": 0, "id": "3bf0b54cbdbd017752e3c477f29e6fd4", "id_penyelenggara": "AFDC243", "no_npwp": "", "sub_tipe_pinjaman": "Onetime Loan / Cash Loan", "email": "nin****ri0@gmail.com", "tgl_perjanjian_borrower": "2021-10-22", "nama_borrower": "AWALUDDIN", "sisa_pinjaman_berjalan": 0, "jenis_pengguna": 1, "no_identitas": "5206020107041139", "tgl_penyaluran_dana": "2021-10-22", "kualitas_pinjaman": "1", "status_pinjaman_ket": "Fully Paid", "penyelesaian_w_oleh": "Default", "tgl_pelaporan_data": "2025-01-16", "nilai_pendanaan": 1100000, "pendanaan_syariah": false, "kualitas_pinjaman_ket": "Lancar", "status_pinjaman": "L", "nama_penjamin": ""}, {"jenis_pengguna_ket": "Individual", "no_hp": "6281*****5063", "agunan": "Tidak Memiliki Agunan", "dpd_max": 0, "no_agunan": "", "tipe_pinjaman": "Multiguna", "reference": "", "pendapatan": 0, "tgl_jatuh_tempo_pinjaman": "2020-10-09", "dpd_terakhir": 0, "id": "ff876f70c3bee9bfb3ca60bbe044ed4a", "id_penyelenggara": "AFDC243", "no_npwp": "", "sub_tipe_pinjaman": "Onetime Loan / Cash Loan", "email": "nin****ri0@gmail.com", "tgl_perjanjian_borrower": "2020-09-09", "nama_borrower": "AWALUDDIN", "sisa_pinjaman_berjalan": 0, "jenis_pengguna": 1, "no_identitas": "5206020107041139", "tgl_penyaluran_dana": "2020-09-09", "kualitas_pinjaman": "1", "status_pinjaman_ket": "Fully Paid", "penyelesaian_w_oleh": "Default", "tgl_pelaporan_data": "2025-09-24", "nilai_pendanaan": 25000, "pendanaan_syariah": false, "kualitas_pinjaman_ket": "Lancar", "status_pinjaman": "L", "nama_penjamin": ""}, {"jenis_pengguna_ket": "Individual", "no_hp": "6282*****2834", "agunan": "Tidak Memiliki Agunan", "dpd_max": 0, "no_agunan": "", "tipe_pinjaman": "Multiguna", "reference": "", "pendapatan": 0, "tgl_jatuh_tempo_pinjaman": "2019-11-26", "dpd_terakhir": 0, "id": "3de47ce9ad5c8c11ed8cc510cc0002eb", "id_penyelenggara": "AFDC243", "no_npwp": "", "sub_tipe_pinjaman": "Onetime Loan / Cash Loan", "email": "awa****ng7@gmail.com", "tgl_perjanjian_borrower": "2019-10-27", "nama_borrower": "AWALUDDIN", "sisa_pinjaman_berjalan": 0, "jenis_pengguna": 1, "no_identitas": "5206020107041139", "tgl_penyaluran_dana": "2019-10-27", "kualitas_pinjaman": "1", "status_pinjaman_ket": "Fully Paid", "penyelesaian_w_oleh": "Default", "tgl_pelaporan_data": "2025-01-16", "nilai_pendanaan": 800000, "pendanaan_syariah": false, "kualitas_pinjaman_ket": "Lancar", "status_pinjaman": "L", "nama_penjamin": ""}, {"jenis_pengguna_ket": "Individual", "no_hp": "6282*****2834", "agunan": "Tidak Memiliki Agunan", "dpd_max": 0, "no_agunan": "", "tipe_pinjaman": "Multiguna", "reference": "", "pendapatan": 0, "tgl_jatuh_tempo_pinjaman": "2018-09-16", "dpd_terakhir": 0, "id": "13065e91e29625bc929a0b0f4dd86c61", "id_penyelenggara": "AFDC243", "no_npwp": "", "sub_tipe_pinjaman": "Onetime Loan / Cash Loan", "email": "awa****ng7@gmail.com", "tgl_perjanjian_borrower": "2018-08-17", "nama_borrower": "AWALUDDIN", "sisa_pinjaman_berjalan": 0, "jenis_pengguna": 1, "no_identitas": "5206020107041139", "tgl_penyaluran_dana": "2018-08-17", "kualitas_pinjaman": "1", "status_pinjaman_ket": "Fully Paid", "penyelesaian_w_oleh": "Default", "tgl_pelaporan_data": "2025-09-22", "nilai_pendanaan": 29000, "pendanaan_syariah": false, "kualitas_pinjaman_ket": "Lancar", "status_pinjaman": "L", "nama_penjamin": ""}, {"jenis_pengguna_ket": "Individual", "no_hp": "6282*****2834", "agunan": "Tidak Memiliki Agunan", "dpd_max": 0, "no_agunan": "", "tipe_pinjaman": "Multiguna", "reference": "", "pendapatan": 0, "tgl_jatuh_tempo_pinjaman": "2018-04-18", "dpd_terakhir": 0, "id": "6e5a6e6eed43af0f75ef10a487e8530b", "id_penyelenggara": "AFDC243", "no_npwp": "", "sub_tipe_pinjaman": "Onetime Loan / Cash Loan", "email": "awa****ng7@gmail.com", "tgl_perjanjian_borrower": "2018-03-19", "nama_borrower": "AWALUDDIN", "sisa_pinjaman_berjalan": 0, "jenis_pengguna": 1, "no_identitas": "5206020107041139", "tgl_penyaluran_dana": "2018-03-19", "kualitas_pinjaman": "1", "status_pinjaman_ket": "Fully Paid", "penyelesaian_w_oleh": "Default", "tgl_pelaporan_data": "2025-09-21", "nilai_pendanaan": 29000, "pendanaan_syariah": false, "kualitas_pinjaman_ket": "Lancar", "status_pinjaman": "L", "nama_penjamin": ""}], "platform_aktif": {"jumlahPlatformAktif": 1, "platform": ["AFDC148"]}}, "feature": {"feature_1": 1, "feature_2": 1, "feature_3": 1, "feature_4": 1, "feature_5": 1, "feature_6": 1, "feature_7": 1, "feature_8": 1, "feature_9": 1, "feature_10": 1, "feature_11": 1, "feature_12": 1, "feature_13": 1, "feature_14": 1, "feature_15": 1, "feature_16": 1, "feature_17": 1, "feature_18": 1, "feature_19": 1, "feature_20": 1, "feature_21": 1, "feature_22": 1, "feature_23": 1, "feature_24": 1, "feature_25": 0, "feature_26": 0, "feature_27": 0, "feature_28": 0, "feature_29": 0, "feature_30": 0, "feature_31": 1, "feature_32": 1, "feature_33": 1, "feature_34": 1, "feature_35": 1, "feature_36": 1, "feature_37": 1, "feature_38": 1, "feature_39": 1, "feature_40": 1, "feature_41": 1, "feature_42": 1, "feature_43": 1, "feature_44": 1, "feature_45": 1, "feature_46": 1, "feature_47": 1, "feature_48": 1, "feature_49": 1, "feature_50": 1, "feature_51": 1, "feature_52": 1, "feature_53": 1, "feature_54": 1, "feature_55": 1, "feature_56": 1, "feature_57": 1, "feature_58": 1, "feature_59": 1, "feature_60": 1, "feature_61": 1, "feature_62": 1, "feature_63": 1, "feature_64": 1, "feature_65": 1, "feature_66": 1, "feature_67": 1, "feature_68": 1, "feature_69": 1, "feature_70": 1, "feature_71": 1, "feature_72": 1, "feature_73": 1, "feature_74": 1, "feature_75": 1, "feature_76": 1, "feature_77": 1, "feature_78": 1, "feature_79": 0, "feature_80": 0, "feature_81": 1, "feature_82": 1, "feature_83": 1, "feature_84": 1, "feature_85": 1, "feature_86": 1, "feature_87": 1, "feature_88": 1, "feature_89": 1, "feature_90": 1, "feature_91": 1, "feature_92": 1, "feature_93": 1, "feature_94": 1, "feature_95": 1, "feature_96": 1, "feature_97": 1, "feature_98": 1, "feature_99": 1, "feature_100": 1, "feature_101": 1, "feature_102": 1, "feature_103": 1, "feature_104": 1, "feature_105": 0, "feature_106": 0, "feature_107": 0, "feature_108": 0, "feature_109": 0, "feature_110": 0, "feature_111": 0, "feature_112": 0, "feature_113": 0, "feature_114": 0, "feature_115": 0, "feature_116": 0, "feature_117": 0, "feature_118": 0, "feature_119": 0, "feature_120": 0, "feature_121": 0, "feature_122": 9, "0119_other_app_max_overdue_day": 0, "feature_123": 1, "feature_sms_cnt_less_10": 1, "feature_124": 0, "feature_cur_money_all": 0, "feature_cur_money_all_add_order": 600000, "feature_cur_money_app_add_order": 600000, "cnt_phone_60_all_clear_order": 0, "feature_1888": 0, "feature_2197": 0, "feature_2506": 0, "feature_2815": 0, "app_phone_loansprogress": 0, "app_ID_loansprogress": 0, "app_bank_loansprogress": 0, "app_gaid_loansprogress": 0, "app_phone_overdue": 0, "app_ID_overdue": 0, "app_bank_overdue": 0, "app_gaid_overdue": 0, "app_90_phone_loansprogress": 0, "app_90_ID_loansprogress": 0, "app_90_bank_loansprogress": 0, "app_90_gaid_loansprogress": 0, "app_90_phone_overdue": 0, "app_90_ID_overdue": 0, "app_90_bank_overdue": 0, "app_90_gaid_overdue": 0, "id_90_app_max_overdue_day": 0, "id_90_product_max_overdue_day": 0, "id_90_all_max_overdue_day": 0, "phone_90_app_max_overdue_day": 0, "phone_90_product_max_overdue_day": 0, "phone_90_all_max_overdue_day": 0, "bank_90_app_max_overdue_day": 0, "bank_90_product_max_overdue_day": 0, "bank_90_all_max_overdue_day": 0, "gaid_90_app_max_overdue_day": 0, "gaid_90_product_max_overdue_day": 0, "gaid_90_all_max_overdue_day": 0, "id_90_all_payout_cnt": 0, "phone_90_all_payout_cnt": 0, "bank_90_all_payout_cnt": 0, "gaid_90_all_payout_cnt": 0, "user_order_age": 0, "phone_app_1_early_repay_2_cnt": 0, "phone_app_3_early_repay_2_cnt": 0, "phone_app_5_early_repay_2_cnt": 0, "phone_app_7_early_repay_2_cnt": 0, "this_to_last_order_apply_time": -999, "has_other_app_loan": 0, "has_other_app_overdue": 0, "has_other_app_apply": 0, "all_user_order_age": -999, "other_app_last_settle_amt": 0, "first_loan_repay_money": 0, "0617_battery_status": 0, "0119_battery_is_charging": 0, "0119_battery_pct": 20, "0126_is_in_black": 0, "0126_is_in_indo_order": 1, "0201_is_in_indo_tele": 1}}}